Workbook

Sheet Dep Calculation
J1: Dep Calculation
B2: 2021 | C2: 2022 | D2: 2023 | E2: 2024 | F2: 2025 | G2: 2026 | I2: 2021 | J2: 2022 | K2: 2023 | L2: 2024 | M2: 2025 | N2: 2026
A3: Adj. Company-Operated Restaurants - Occupancy & other op. expenses | B3: =Raw!C56 -> 2273.3 | I3: =B3/SUM($B$3:$B$4)*$B$8 -> 921.54411
A4: Adj. Franchised Restaurants Occupancy Expenses | B4: =Raw!C57 -> 2335 | I4: =B4/SUM($B$3:$B$4)*$B$8 -> 946.55589
A8: Total Dep | B8: =Raw!C76 -> 1868.1 | C8: =Raw!D76 -> 1870.6
A9: dep | B9: =Raw!C77 -> 1530.7 | C9: =Raw!D77 -> 1454

Sheet Raw
A2: Information | C2: 12 months | D2: 12 months | E2: 12 months | F2: 12 months | G2: 12 months | H2: 3 | I2: 3
C3: Dec. 31, 2021 | D3: Dec. 31, 2022 | E3: Dec. 31, 2023 | F3: Dec. 31, 2024 | G3: Dec. 31, 2025 | H3: 46112 | I3: 45747
A4: SEGMENT REVENUE
A5: Segmental Net Operating Revenue (GAAP - Reported)
A6: Company-operated sales: | C6: 9787 | D6: 8748 | E6: 9742 | F6: 15715 | G6: 16548 | H6: 2317 | I6: 2132
A7: Franchised revenues: | C7: 13085 | D7: 14106 | E7: 15436 | F7: 9782 | G7: 9690 | H7: 4007 | I7: 3661
A8: Total Other revenues | C8: 350 | D8: 329 | E8: 316 | F8: 423 | G8: 647 | H8: 193 | I8: 162
A9: Total Revenues | C9: =SUM(C6:C8) -> 23222 | D9: =SUM(D6:D8) -> 23183 | E9: =SUM(E6:E8) -> 25494 | F9: =SUM(F6:F8) -> 25920 | G9: =SUM(G6:G8) -> 26885 | H9: =SUM(H6:H8) -> 6517 | I9: =SUM(I6:I8) -> 5955
A10: Source | C10: 2021 10K, Page 13 | D10: 2022 10K, Page 13 | E10: 2023 10K, Page 14 | F10: 2024 10K, Page 14 | G10: 2025 10K, Page 14 | H10: 2026 10Q Q1, Page 4 | I10: 2026 10Q Q1, Page 11
A12: % Change Organic Revenues (non-GAAP) | H12: 3m-o-3m
A13: Company-operated sales: | C13: 18 % | D13: 4 % | E13: 0.12 | F13: 0.02 | G13: 0.04 | H13: 0.03
A14: Franchised revenues: | C14: 19 % | D14: 14 % | E14: 0.09 | F14: 0.01 | G14: 0.02 | H14: 0.05
A15: Total Company-operated sales and Franchised revenues: | C15: 19 % | D15: 0.06 | E15: 0.1 | F15: 0.01 | G15: 0.01 | H15: 0.04
A16: Total Other revenues | C16: — % | D16: 0.03 | E16: 0.03 | F16: 0.34 | G16: 0.52 | H16: 0.16
A17: Total Revenues | C17: 18 % | D17: 0.06 | E17: 0.1 | F17: 0.02 | G17: 0.02 | H17: 0.04
C18: 2021 10K, Page 13 | D18: 2022 10K, Page 13 | E18: 2023 10K, Page 14 | F18: 2024 10K, Page 14 | G18: 2025 10K, Page 14 | H18: 2026 8K, Page 11
A21: INCOME STATEMENT ITEMS
A22: Reported Numbers from Inc. Statement (GAAP)
A23: Sales by Company Operated Restaurants | C23: 9787.4 | D23: 8748.4 | E23: 9741.6 | F23: 9782 | G23: 9690 | H23: 2317
A24: Revenues from franchised operations | C24: 13085.4 | D24: 14105.8 | E24: 15436.5 | F24: 15715 | G24: 16548 | H24: 4007
A25: Other Revenues | C25: 350.1 | D25: 328.4 | E25: 315.6 | F25: 423 | G25: 647 | H25: 193
A26: Net Operating Revenue | C26: =C23+C24+C25 -> 23222.9 | D26: =D23+D24+D25 -> 23182.6 | E26: =E23+E24+E25 -> 25493.7 | F26: =F23+F24+F25 -> 25920 | G26: =G23+G24+G25 -> 26885 | H26: =H23+H24+H25 -> 6517
A27: Company-Operated Restaurants - Food & Paper | C27: 3096.8 | D27: 2737.3 | E27: 3039 | F27: 2995 | G27: 3006 | H27: 0
A28: Company-Operated Restaurants - Payroll | C28: 2677.2 | D28: 2617.4 | E28: 2885.8 | F28: 2959 | G28: 2905 | H28: 0
A29: Company-Operated Restaurants - Occupancy & other op. expenses | C29: 2273.3 | D29: 2026.2 | E29: 2299.3 | F29: 2381 | G29: 2358 | H29: 2032
A30: Franchised Restaurants Occupancy Expenses | C30: 2335 | D30: 2349.7 | E30: 2474.6 | F30: 2536 | G30: 2618 | H30: 676
A31: Other Restaurant Expenses | C31: 260.4 | D31: 244.8 | E31: 232.5 | F31: 339 | G31: 564 | H31: 166
A32: Selling, general & administrative expenses
A33: Depreciation & Amortization | C33: 329.7 | D33: 370.4 | E33: 381.7 | F33: 447 | G33: 457 | H33: 111
A34: Other | C34: 2377.8 | D34: 2492.2 | E34: 2435.2 | F34: 2412 | G34: 2583 | H34: 648
A35: Other Operating (Income) Expense, Net | C35: -483.3 | D35: 973.6 | E35: 98.9 | F35: 139 | G35: 2 | H35: -69
A36: OPERATING INCOME | C36: =C26-SUM(C27:C35) -> 10356 | D36: =D26-SUM(D27:D35) -> 9371 | E36: =E26-SUM(E27:E35) -> 11646.7 | F36: =F26-SUM(F27:F35) -> 11712 | G36: =G26-SUM(G27:G35) -> 12392 | H36: =H26-SUM(H27:H35) -> 2953
A37: Interest Expense--net of capitalized interest | C37: 1185.8 | D37: 1207 | E37: 1360.8 | F37: 1506 | G37: 1582 | H37: 400
A38: Nonoperating (Income) expense, net | C38: 42.3 | D38: 338.6 | E38: -236.3 | F38: -139 | G38: -87 | H38: 11
A39: INCOME BEFORE INCOME TAXES | C39: =C36-C37-C38 -> 9127.9 | D39: =D36-D37-D38 -> 7825.4 | E39: =E36-E37-E38 -> 10522.2 | F39: =F36-F37-F38 -> 10345 | G39: =G36-G37-G38 -> 10897 | H39: =H36-H37-H38 -> 2542
A40: Tax | C40: 1582.7 | D40: 1648 | E40: 2053.4 | F40: 2121 | G40: 2334 | H40: 559
A41: CONSOL. NET INCOME | C41: =C39-C40 -> 7545.2 | D41: =D39-D40 -> 6177.4 | E41: =E39-E40 -> 8468.8 | F41: =F39-F40 -> 8224 | G41: =G39-G40 -> 8563 | H41: =H39-H40 -> 1983
A42: Profit Attributable to NCI (from Inc. St.) | C42: 0 | D42: 0 | E42: 0 | F42: 0 | G42: 0 | H42: 0
A43: NET INCOME ATTRIBUTABLE TO SH. HOLDERS | C43: =C41-C42 -> 7545.2 | D43: =D41-D42 -> 6177.4 | E43: =E41-E42 -> 8468.8 | F43: =F41-F42 -> 8224 | G43: =G41-G42 -> 8563 | H43: =H41-H42 -> 1983
A44: Basic Number of Shares | C44: 746.3 | D44: 736.5 | E44: 727.9 | F44: 718.3 | G44: 713.4 | H44: 710.7
A45: Diluted Number of Shares | C45: 751.8 | D45: 741.3 | E45: 732.3 | F45: 721.9 | G45: 716.4 | H45: 713.5
A46: Source | C46: 2021 10K, Page 39 | D46: 2022 10K, Page 36 | E46: 2023 10K, Page 38 | F46: 2024 10K, Page 41 | G46: 2025 10K, Page 39 | H46: 2026 10Q Page 9
A49: Comparable Numbers for Adj. Inc. Statement (non-GAAP)
A50: Adj. Sales by Company Operated Restaurants | C50: =C23 -> 9787.4 | D50: 8748.4 | E50: 9741.6 | F50: 9782 | G50: 9690 | H50: 2317
A51: Adj. Revenues from franchised operations | C51: =C24 -> 13085.4 | D51: 14105.8 | E51: 15436.5 | F51: 15715 | G51: 16548 | H51: 4007
A52: Adj. Other Revenues | C52: =C25 -> 350.1 | D52: 328.4 | E52: 315.6 | F52: 423 | G52: 647 | H52: 193
A53: Adj. Net Operating Revenue | C53: =SUM(C50:C52) -> 23222.9 | D53: =D50+D51+D52 -> 23182.6 | E53: =E50+E51+E52 -> 25493.7 | F53: =F50+F51+F52 -> 25920 | G53: =G50+G51+G52 -> 26885 | H53: =H50+H51+H52 -> 6517
A54: Adj. Company-Operated Restaurants - Food & Paper | C54: =C27 -> 3096.8 | D54: 2737.3 | E54: 3039 | F54: 2995 | G54: 3006 | H54: 0
A55: Adj. Company-Operated Restaurants - Payroll | C55: =C28 -> 2677.2 | D55: 2617.4 | E55: 2885.8 | F55: 2959 | G55: 2905 | H55: 0
A56: Adj. Company-Operated Restaurants - Occupancy & other op. expenses | C56: =C29 -> 2273.3 | D56: 2026.2 | E56: 2299.3 | F56: 2381 | G56: 2358 | H56: 2032
A57: Adj. Franchised Restaurants Occupancy Expenses | C57: =C30 -> 2335 | D57: 2349.7 | E57: 2474.6 | F57: 2536 | G57: 2618 | H57: 676
A58: Adj. Other Restaurant Expenses | C58: =C31 -> 260.4 | D58: 244.8 | E58: 232.5 | F58: 339 | G58: 564 | H58: 166
A59: Adj. Depreciation & Amortization + Other | C59: =C33 -> 329.7 | D59: 370.4 | E59: 381.7 | F59: 447 | G59: 457 | H59: 111
A60: Adj. SG&A | C60: =C34 -> 2377.8 | D60: 2492.2 | E60: 2435.2 | F60: 2412 | G60: 2583 | H60: 648
A61: Adj. Other Operating (Income) Expense, Net | C61: =C35-339+54 -> -768.3 | D61: =D35+1281-271 -> 1983.6 | E61: =E35+290 -> 388.9 | F61: =F35+221+70 -> 430 | G61: =G35+229 -> 231 | H61: =H35+47 -> -22
A62: Adj. OPERATING INCOME | C62: =C53-SUM(C54:C61) -> 10641 | D62: =D53-SUM(D54:D61) -> 8361 | E62: =E53-SUM(E54:E61) -> 11356.7 | F62: =F53-SUM(F54:F61) -> 11421 | G62: =G53-SUM(G54:G61) -> 12163 | H62: =H53-SUM(H54:H61) -> 2906
A63: Adj. Interest Expense--net of capitalized interest | C63: =C37 -> 1185.8 | D63: 1207 | E63: 1360.8 | F63: 1506 | G63: 1582 | H63: 400
A64: Adj. Nonoperating (Income) expense, net | C64: =C38 -> 42.3 | D64: 338.6 | E64: -236.3 | F64: -139 | G64: -87 | H64: 11
A65: Adj. INCOME BEFORE INCOME TAXES | C65: =C62-C63-C64 -> 9412.9 | D65: =D62-D63-D64 -> 6815.4 | E65: =E62-E63-E64 -> 10232.2 | F65: =F62-F63-F64 -> 10054 | G65: =G62-G63-G64 -> 10668 | H65: =H62-H63-H64 -> 2495
A66: Adj. Tax | C66: =C40+364 -> 1946.7 | D66: =D40-537 -> 1111 | E66: 2053.4 | F66: 2121 | G66: 2334 | H66: 559
A67: Adj. CONSOL. NET INCOME | C67: =C65-C66 -> 7466.2 | D67: =D65-D66 -> 5704.4 | E67: =E65-E66 -> 8178.8 | F67: =F65-F66 -> 7933 | G67: =G65-G66 -> 8334 | H67: =H65-H66 -> 1936
A68: Adj. Profit Attributable to NCI (from Inc. St.) | C68: 0 | D68: 0 | E68: 0 | F68: 0 | G68: 0 | H68: 0
A69: Adj. NET INCOME ATTRIBUTABLE TO SH. HOLDERS | C69: =C67-C68 -> 7466.2 | D69: =D67-D68 -> 5704.4 | E69: =E67-E68 -> 8178.8 | F69: =F67-F68 -> 7933 | G69: =G67-G68 -> 8334 | H69: =H67-H68 -> 1936
A70: Basic Number of shares | C70: 746.3 | D70: 736.5 | E70: 727.9 | F70: 718.3 | G70: 713.4 | H70: 710.7
A71: Diluted Number os shares | C71: =C45 -> 751.8 | D71: 741.3 | E71: 732.3 | F71: 721.9 | G71: 716.4 | H71: 713.5
A72: source | C72: 2021 Q4 ER page 3
A75: FEW CASHFLOW STATEMENT ITEMS
A76: Total Depreciation & Amortization (from CFS) | C76: 1868.1 | D76: 1870.6 | E76: 1978.2 | F76: 2097 | G76: 2199 | H76: 566
A77: Depreciation During the year (PPE dep) | C77: 1530.7 | D77: 1454 | E77: 1501 | F77: 1500 | G77: 1600 | H77: =H82*H76 -> 429.97447
A78: Difference | C78: =C76-C77 -> 337.4 | D78: =D76-D77 -> 416.6 | E78: =E76-E77 -> 477.2 | F78: =F76-F77 -> 597 | G78: =G76-G77 -> 599 | H78: =H76-H77 -> 136.02553
A79: Depreciation & Amortization + Other (from IS) | C79: 329.7 | D79: 370.4 | E79: 381.7 | F79: 447 | G79: 457 | H79: =H76*H83 -> 111.89111
A80: Corporate Dep. & Amort. (Note - Operating Segments ) | C80: 301 | D80: 317.6 | E80: 329.8 | F80: 387 | G80: 415 | H80: 587
A81: Difference (assuming this as Special Items) (ie., other portion of D&A) | C81: =C76-C77-C79 -> 7.7 | D81: =D76-D77-D79 -> 46.2 | E81: =E76-E77-E79 -> 95.5 | F81: =F76-F77-F79 -> 150 | G81: =G76-G77-G79 -> 142 | H81: =H76-H77-H79 -> 24.134418
A82: Depreciation During the year (PPE dep) as % of Total D&A | C82: =C77/C76 -> 0.81938868 | D82: =D77/D76 -> 0.77729071 | E82: =E77/E76 -> 0.7587706 | F82: =F77/F76 -> 0.71530758 | G82: =G77/G76 -> 0.72760346 | H82: =AVERAGE(C82:G82) -> 0.75967221
A83: Depreciation & Amortization + Other (from IS) as % of Total D&A | C83: =C79/C76 -> 0.17648948 | D83: =D79/D76 -> 0.19801133 | E83: =E79/E76 -> 0.19295319 | F83: =F79/F76 -> 0.21316166 | G83: =G79/G76 -> 0.20782174 | H83: =AVERAGE(C83:G83) -> 0.19768748
A84: Share-based compensation Expense | C84: 139.2 | D84: 166.7 | E84: 175.2 | F84: 172 | G84: 165 | H84: 60
A85: Equity Dividend/Common stock dividends | C85: 3918.6 | D85: 4168.2 | E85: 4532.8 | F85: 4870 | G85: 5115 | H85: 1323
A87: Source | C87: 2021 10K, Page 42, 51 | D87: 2022 10K, Page 39, 48 | E87: 2023 10K, Page 41, 49 | F87: 2024 10K, Page 44, 54 | G87: 2025 10K, Page 42, 52 | H87: 2026 10Q Page 12
A89: BALANCE SHEET ITEMS
A90: Current Assets
A91: Cash and cash equivalents | C91: 4709.2 | D91: 2583.8 | E91: 4579.3 | F91: 1085 | G91: 774 | H91: 1170
A92: Total Cash, CE & Short term investments | C92: 4709.2 | D92: 2583.8 | E92: 4579.3 | F92: 1085 | G92: 774 | H92: 1170
A93: Accounts and notes receivable | C93: 1872.4 | D93: 2115 | E93: 2488 | F93: 2383 | G93: 2466 | H93: 2432
A94: Inventories | C94: 55.6 | D94: 52 | E94: 52.8 | F94: 56 | G94: 61 | H94: 61
A95: Prepaid expenses and other current assets | C95: 511.3 | D95: 673.4 | E95: 866.3 | F95: 1074 | G95: 863 | H95: 1046
A96: Total Current assets | C96: =SUM(C92:C95) -> 7148.5 | D96: =SUM(D92:D95) -> 5424.2 | E96: =SUM(E92:E95) -> 7986.4 | F96: =SUM(F92:F95) -> 4598 | G96: =SUM(G92:G95) -> 4164 | H96: =SUM(H92:H95) -> 4709
A97: Investments in and advances to affiliates | C97: 1201.2 | D97: 1064.5 | E97: 1080.2 | F97: 2710 | G97: 2820 | H97: 2865
A98: PPE-Net property and equipment | C98: 24720.6 | D98: 23773.6 | E98: 24907.6 | F98: 25295 | G98: 28241 | H98: 28245
A99: Goodwill | C99: 2782.5 | D99: 2900.4 | E99: 3040.4 | F99: 3145 | G99: 3354 | H99: 3349
A100: Other Non-Current Assets | C100: =4449.5+13552 -> 18001.5 | D100: 17272.9 | E100: 19132.2 | F100: 19434 | G100: 20937 | H100: 20870
A101: Other Intangible Assets | C101: 0 | D101: 0 | E101: 0 | F101: 0 | G101: 0 | H101: 0
A102: Total Assets | C102: =SUM(C96:C101) -> 53854.3 | D102: =SUM(D96:D101) -> 50435.6 | E102: =SUM(E96:E101) -> 56146.8 | F102: =SUM(F96:F101) -> 55182 | G102: =SUM(G96:G101) -> 59516 | H102: =SUM(H96:H101) -> 60038
A104: Current Liabilities
A105: Accounts payable and accrued expenses | C105: 1006.8 | D105: 980.2 | E105: 1102.9 | F105: 1029 | G105: 1149 | H105: 1091
A106: Accrued Interest | C106: 363.3 | D106: 393.4 | E106: 468.9 | F106: 482 | G106: 533 | H106: 448
A107: Accrued Payroll & Other Liabilities | C107: 1347 | D107: 1237.4 | E107: 1433.6 | F107: 1129 | G107: 1488 | H107: 1257
A108: Short term borrowings & Current maturities of long-term debt | C108: 0 | D108: 0 | E108: 2192.4 | F108: 0 | G108: 0 | H108: 0
A109: Accrued income taxes | C109: 360.7 | D109: 274.9 | E109: 705.1 | F109: 361 | G109: 250 | H109: 391
A110: Other taxes | C110: 236.7 | D110: 255.1 | E110: 268 | F110: 224 | G110: 247 | H110: 253
A111: Lease liability | C111: 705.5 | D111: 661.1 | E111: 688.1 | F111: 636 | G111: 694 | H111: 707
...

Sheet Revenue Segments
A1: McDONALD’S CORPORATION
A2: (in USD millions) | C2: Valuation Date
A3: Segment Information | C3: 12 months | D3: 12 months | E3: 12 months | F3: 12 months | G3: 12 months | I3: 3 | J3: 3 | L3: 9 | M3: 9 | O3: 12 months | P3: 12 months | Q3: 12 months | R3: 12 months | S3: 12 months | T3: 12 months
C4: Dec. 31, 2021 | D4: Dec. 31, 2022 | E4: Dec. 31, 2023 | F4: Dec. 31, 2024 | G4: Dec. 31, 2025 | I4: 45747 | J4: 46112 | L4: Dec. 31, 2025 | M4: Dec. 31, 2026 | O4: Dec. 31, 2026 | P4: Dec. 31, 2027 | Q4: Dec. 31, 2028 | R4: Dec. 31, 2029 | S4: Dec. 31, 2030 | T4: Dec. 31, 2031
A6: Company-operated sales: | C6: =Raw!C6 -> 9787 | D6: =Raw!D6 -> 8748 | E6: =Raw!E6 -> 9742 | F6: =Raw!F6 -> 15715 | G6: =Raw!G6 -> 16548 | I6: =Raw!I6 -> 2132 | J6: =Raw!H6 -> 2317 | L6: =G6-I6 -> 14416 | M6: =L6*(1+J8) -> 14848.48 | O6: =J6+M6 -> 17165.48 | P6: =O6*(1+$O8) -> 17937.927 | Q6: =P6*(1+$O8) -> 18745.133 | R6: =Q6*(1+$O8) -> 19588.664 | S6: =R6*(1+$O8) -> 20470.154 | T6: =S6*(1+$O8) -> 21391.311
A7: Reported Y-o-Y Growth % (GAAP)
A8: Organic Growth % (non-GAAP) | C8: =Raw!C13 -> 18 % | D8: =Raw!D13 -> 4 % | E8: =Raw!E13 -> 0.12 | F8: =Raw!F13 -> 0.02 | G8: =Raw!G13 -> 0.04 | H8: =AVERAGE(C8:G8) -> 0.06 | J8: =Raw!H13 -> 0.03 | O8: =AVERAGE(H8,J8) -> 0.045
A10: Franchised revenues: | C10: =Raw!C7 -> 13085 | D10: =Raw!D7 -> 14106 | E10: =Raw!E7 -> 15436 | F10: =Raw!F7 -> 9782 | G10: =Raw!G7 -> 9690 | I10: =Raw!I7 -> 3661 | J10: =Raw!H7 -> 4007 | L10: =G10-I10 -> 6029 | M10: =L10*(1+J12) -> 6330.45 | O10: =J10+M10 -> 10337.45 | P10: =O10*(1+$O12) -> 10802.635 | Q10: =P10*(1+$O12) -> 11288.754 | R10: =Q10*(1+$O12) -> 11796.748 | S10: =R10*(1+$O12) -> 12327.601 | T10: =S10*(1+$O12) -> 12882.343
A11: Reported Y-o-Y Growth % (GAAP)
A12: Organic Growth % (non-GAAP) | C12: =Raw!C14 -> 19 % | D12: =Raw!D14 -> 14 % | E12: =Raw!E14 -> 0.09 | F12: =Raw!F14 -> 0.01 | G12: =Raw!G14 -> 0.02 | H12: =AVERAGE(C12:G12) -> 0.04 | J12: =Raw!H14 -> 0.05 | O12: =AVERAGE(H12,J12) -> 0.045
A14: Total Other revenues: | C14: =Raw!C8 -> 350 | D14: =Raw!D8 -> 329 | E14: =Raw!E8 -> 316 | F14: =Raw!F8 -> 423 | G14: =Raw!G8 -> 647 | I14: =Raw!I8 -> 162 | J14: =Raw!H8 -> 193 | L14: =G14-I14 -> 485 | M14: =L14*(1+J16) -> 562.6 | O14: =J14+M14 -> 755.6 | P14: =O14*(1+$O16) -> 902.942 | Q14: =P14*(1+$O16) -> 1079.0157 | R14: =Q14*(1+$O16) -> 1289.4237 | S14: =R14*(1+$O16) -> 1540.8614 | T14: =S14*(1+$O16) -> 1841.3293
A15: Reported Y-o-Y Growth % (GAAP)
A16: Organic Growth % (non-GAAP) | C16: =Raw!C16 -> — % | D16: =Raw!D16 -> 0.03 | E16: =Raw!E16 -> 0.03 | F16: =Raw!F16 -> 0.34 | G16: =Raw!G16 -> 0.52 | H16: =AVERAGE(C16:G16) -> 0.23 | J16: =Raw!H16 -> 0.16 | O16: =AVERAGE(H16,J16) -> 0.195
A18: Total Division | C18: =SUM(C6,C10,C14) -> 23222 | D18: =SUM(D6,D10,D14) -> 23183 | E18: =SUM(E6,E10,E14) -> 25494 | F18: =SUM(F6,F10,F14) -> 25920 | G18: =SUM(G6,G10,G14) -> 26885 | I18: =SUM(I6,I10,I14) -> 5955 | J18: =SUM(J6,J10,J14) -> 6517 | L18: =SUM(L6,L10,L14) -> 20930 | M18: =SUM(M6,M10,M14) -> 21741.53 | O18: =SUM(O6,O10,O14) -> 28258.53 | P18: =SUM(P6,P10,P14) -> 29643.504 | Q18: =SUM(Q6,Q10,Q14) -> 31112.903 | R18: =SUM(R6,R10,R14) -> 32674.836 | S18: =SUM(S6,S10,S14) -> 34338.617 | T18: =SUM(T6,T10,T14) -> 36114.984
A21: ALTERNATIVE METHOD
A23: Management guidance | C23: 0.06
A25: Total Division | G25: =G18 -> 26885 | J25: =J18 -> 6517 | M25: =G25*(1+C23)-J25 -> 21981.1 | O25: =J25+M25 -> 28498.1 | P25: =O25*(1+$C$23) -> 30207.986 | Q25: =P25*(1+$C$23) -> 32020.465 | R25: =Q25*(1+$C$23) -> 33941.693 | S25: =R25*(1+$C$23) -> 35978.195 | T25: =S25*(1+$C$23) -> 38136.886
A27: 6.0% growth assumed based on management-reported 6% constant-currency Systemwide sales growth and expected restaurant expansion contribution of 2.5% in FY2026.Refer FORM 8-K (page 16), Date of report: May 7, 2026.

Sheet McD IS
A1: McDONALD’S CORPORATION | G1: HISTORICAL STUB | H1: FORECAST STUB
A2: (in USD million except per Share Data)
A3: Income Statement | B3: 12 | C3: 12 | D3: 12 | E3: 12 | F3: 12 | G3: 3 | H3: 9 | I3: 12 | J3: 12 | K3: 12 | L3: 12 | M3: 12 | N3: 12
B4: 44561 | C4: 44926 | D4: 45291 | E4: 45657 | F4: 46022 | G4: 46112 | H4: 46387 | I4: 46387 | J4: 46752 | K4: 47118 | L4: 47483 | M4: 47848 | N4: 48213
A6: Net Operating Revenues - Reported | B6: =Raw!C26 -> 23222.9 | C6: =Raw!D26 -> 23182.6 | D6: =Raw!E26 -> 25493.7 | E6: =Raw!F26 -> 25920 | F6: =Raw!G26 -> 26885 | G6: =Raw!H26 -> 6517
A7: Other Items (affecting Comparability) | B7: =B8-B6 -> 0 | C7: =C8-C6 -> 0 | D7: =D8-D6 -> 0 | E7: =E8-E6 -> 0 | F7: =F8-F6 -> 0 | G7: =G8-G6 -> 0
A8: Net Operating Revenues - Normalised/Adjusted | B8: =Raw!C53 -> 23222.9 | C8: =Raw!D53 -> 23182.6 | D8: =Raw!E53 -> 25493.7 | E8: =Raw!F53 -> 25920 | F8: =Raw!G53 -> 26885 | G8: =Raw!H53 -> 6517 | H8: ='Revenue Segments'!M25 -> 21981.1 | I8: =H8+G6 -> 28498.1 | J8: ='Revenue Segments'!P25 -> 30207.986 | K8: ='Revenue Segments'!Q25 -> 32020.465 | L8: ='Revenue Segments'!R25 -> 33941.693 | M8: ='Revenue Segments'!S25 -> 35978.195 | N8: ='Revenue Segments'!T25 -> 38136.886
A10: Cost of Goods and Services Sold - Reported | B10: =SUM(Raw!C27:C31) -> 10642.7 | C10: =SUM(Raw!D27:D31) -> 9975.4 | D10: =SUM(Raw!E27:E31) -> 10931.2 | E10: =SUM(Raw!F27:F31) -> 11210 | F10: =SUM(Raw!G27:G31) -> 11451 | G10: =SUM(Raw!H27:H31) -> 2874
A11: Impact of Special Items
A12: Cost of Goods and Services Sold - Normalised/Adjusted | B12: =SUM(Raw!C27:C31) -> 10642.7 | C12: =SUM(Raw!D27:D31) -> 9975.4 | D12: =SUM(Raw!E27:E31) -> 10931.2 | E12: =SUM(Raw!F27:F31) -> 11210 | F12: =SUM(Raw!G27:G31) -> 11451 | G12: =SUM(Raw!H27:H31) -> 2874
A13: Depreciation & Amort. (PPE) | B13: =Raw!C77 -> 1530.7 | C13: =Raw!D77 -> 1454 | D13: =Raw!E77 -> 1501 | E13: =Raw!F77 -> 1500 | F13: =Raw!G77 -> 1600 | G13: =Raw!H77 -> 429.97447
A14: Cost of Goods and Services Sold - Normalized (after removing Dep.) | B14: =B12-B13 -> 9112 | C14: =C12-C13 -> 8521.4 | D14: =D12-D13 -> 9430.2 | E14: =E12-E13 -> 9710 | F14: =F12-F13 -> 9851 | G14: =G12-G13 -> 2444.0255 | H14: =H8*H79 -> 8227.8982 | I14: =H14+G14 -> 10671.924 | J14: =J8*$H$79 -> 11307.361 | K14: =K8*$H$79 -> 11985.803 | L14: =L8*$H$79 -> 12704.951 | M14: =M8*$H$79 -> 13467.248 | N14: =N8*$H$79 -> 14275.283
A16: Gross Profit - Reported | B16: =B6-B10 -> 12580.2 | C16: =C6-C10 -> 13207.2 | D16: =D6-D10 -> 14562.5 | E16: =E6-E10 -> 14710 | F16: =F6-F10 -> 15434 | G16: =G6-G10 -> 3643
A17: Gross Profit - Normalised/Adjusted | B17: =B8-B14 -> 14110.9 | C17: =C8-C14 -> 14661.2 | D17: =D8-D14 -> 16063.5 | E17: =E8-E14 -> 16210 | F17: =F8-F14 -> 17034 | G17: =G8-G14 -> 4072.9745 | H17: =H8-H14 -> 13753.202 | I17: =H17+G17 -> 17826.176 | J17: =J8-J14 -> 18900.625 | K17: =K8-K14 -> 20034.662 | L17: =L8-L14 -> 21236.742 | M17: =M8-M14 -> 22510.947 | N17: =N8-N14 -> 23861.604
A19: Selling, General and Administrative Expense - Reported | B19: =Raw!C34+B20 -> 2385.5 | C19: =Raw!D34+C20 -> 2538.4 | D19: =Raw!E34+D20 -> 2530.7 | E19: =Raw!F34+E20 -> 2562 | F19: =Raw!G34+F20 -> 2725 | G19: =Raw!H34+G20 -> 672.13442
A20: Impact of Special Items | B20: =Raw!C81 -> 7.7 | C20: =Raw!D81 -> 46.2 | D20: =Raw!E81 -> 95.5 | E20: =Raw!F81 -> 150 | F20: =Raw!G81 -> 142 | G20: =Raw!H81 -> 24.134418
A21: Selling, General and Administrative Expense - Normalised/Adjusted | B21: =B19-B20 -> 2377.8 | C21: =C19-C20 -> 2492.2 | D21: =D19-D20 -> 2435.2 | E21: =E19-E20 -> 2412 | F21: =F19-F20 -> 2583 | G21: =G19-G20 -> 648 | H21: =H8*H81 -> 2176.0508 | I21: =H21+G21 -> 2824.0508 | J21: =J8*$H$81 -> 2990.4833 | K21: =K8*$H$81 -> 3169.9123 | L21: =L8*$H$81 -> 3360.107 | M21: =M8*$H$81 -> 3561.7134 | N21: =N8*$H$81 -> 3775.4162
A23: Other Cost and Expense, Operating - Reported | B23: =Raw!C35 -> -483.3 | C23: =Raw!D35 -> 973.6 | D23: =Raw!E35 -> 98.9 | E23: =Raw!F35 -> 139 | F23: =Raw!G35 -> 2 | G23: =Raw!H35 -> -69
A24: Impact of Special Items | B24: =B25-B23 -> -285 | C24: =C25-C23 -> 1010 | D24: =D25-D23 -> 290 | E24: =E25-E23 -> 291 | F24: =F25-F23 -> 229 | G24: =G25-G23 -> 47
A25: Other Cost and Expense, Operating - Normalised/Adjusted | B25: =Raw!C61 -> -768.3 | C25: =Raw!D61 -> 1983.6 | D25: =Raw!E61 -> 388.9 | E25: =Raw!F61 -> 430 | F25: =Raw!G61 -> 231 | G25: =Raw!H61 -> -22 | H25: =H8*H83 -> 328.0352 | I25: =H25+G25 -> 306.0352 | J25: =J8*$H$83 -> 450.80923 | K25: =K8*$H$83 -> 477.85779 | L25: =L8*$H$83 -> 506.52926 | M25: =M8*$H$83 -> 536.92101 | N25: =N8*$H$83 -> 569.13627
A27: EBITDA - Normalized/Adjusted | B27: =B17-B21-B25 -> 12501.4 | C27: =C17-C21-C25 -> 10185.4 | D27: =D17-D21-D25 -> 13239.4 | E27: =E17-E21-E25 -> 13368 | F27: =F17-F21-F25 -> 14220 | G27: =G17-G21-G25 -> 3446.9745 | H27: =H17-H21-H25 -> 11249.116 | I27: =H27+G294 -> 11249.116 | J27: =J17-J21-J25 -> 15459.332 | K27: =K17-K21-K25 -> 16386.892 | L27: =L17-L21-L25 -> 17370.106 | M27: =M17-M21-M25 -> 18412.312 | N27: =N17-N21-N25 -> 19517.051
A29: Total Depreciation & Amortization Expense (Reported) | B29: =Raw!C76 -> 1868.1 | C29: =Raw!D76 -> 1870.6 | D29: =Raw!E76 -> 1978.2 | E29: =Raw!F76 -> 2097 | F29: =Raw!G76 -> 2199 | G29: =Raw!H76 -> 566
A30: Impact of Special Items | B30: =Raw!C81 -> 7.7 | C30: =Raw!D81 -> 46.2 | D30: =Raw!E81 -> 95.5 | E30: =Raw!F81 -> 150 | F30: =Raw!G81 -> 142 | G30: =Raw!H81 -> 24.134418
A31: Total Depreciation & Amortization Expense (Normalized) | B31: =B29-B30 -> 1860.4 | C31: =C29-C30 -> 1824.4 | D31: =D29-D30 -> 1882.7 | E31: =E29-E30 -> 1947 | F31: =F29-F30 -> 2057 | G31: =G29-G30 -> 541.86558 | H31: ='Fixed Assets Schedule'!H9 -> 1611.7207 | I31: =H31+G31 -> 2153.5863 | J31: ='Fixed Assets Schedule'!I9 -> 2264.9842 | K31: ='Fixed Assets Schedule'!J9 -> 2348.9096 | L31: ='Fixed Assets Schedule'!K9 -> 2441.518 | M31: ='Fixed Assets Schedule'!L9 -> 2543.0744 | N31: ='Fixed Assets Schedule'!M9 -> 2653.8777
A33: Operating Income (EBIT) - Reported | B33: =B16-B19-B23 -> 10678 | C33: =C16-C19-C23 -> 9695.2 | D33: =D16-D19-D23 -> 11932.9 | E33: =E16-E19-E23 -> 12009 | F33: =F16-F19-F23 -> 12707 | G33: =G16-G19-G23 -> 3039.8656
A34: Operating Income (EBIT) - Normalised/Adjusted | B34: =B27-B31 -> 10641 | C34: =C27-C31 -> 8361 | D34: =D27-D31 -> 11356.7 | E34: =E27-E31 -> 11421 | F34: =F27-F31 -> 12163 | G34: =G27-G31 -> 2905.1089 | H34: =H27-H29 -> 11249.116 | I34: =H34+G34 -> 14154.225 | J34: =J27-J29 -> 15459.332 | K34: =K27-K29 -> 16386.892 | L34: =L27-L29 -> 17370.106 | M34: =M27-M29 -> 18412.312 | N34: =N27-N29 -> 19517.051
A36: Interest Expense-Reported | B36: =Raw!C37 -> 1185.8 | C36: =Raw!D37 -> 1207 | D36: =Raw!E37 -> 1360.8 | E36: =Raw!F37 -> 1506 | F36: =Raw!G37 -> 1582 | G36: =Raw!H37 -> 400
A37: Impact of Special Items
A38: Interest expense - Normalised/Adjusted | B38: =Raw!C63 -> 1185.8 | C38: =Raw!D63 -> 1207 | D38: =Raw!E63 -> 1360.8 | E38: =Raw!F63 -> 1506 | F38: =Raw!G63 -> 1582 | G38: =Raw!H63 -> 400 | H38: ='Debt Schedule'!H13 -> 1152.9111 | I38: =H38+G38 -> 1552.9111 | J38: ='Debt Schedule'!I13 -> 1475.868 | K38: ='Debt Schedule'!J13 -> 1315.5155 | L38: ='Debt Schedule'!K13 -> 1146.8071 | M38: ='Debt Schedule'!L13 -> 1019.399 | N38: ='Debt Schedule'!M13 -> 961.69354
A40: Nonoperating (Income) expense, net - Reported | B40: =Raw!C38 -> 42.3 | C40: =Raw!D38 -> 338.6 | D40: =Raw!E38 -> -236.3 | E40: =Raw!F38 -> -139 | F40: =Raw!G38 -> -87 | G40: =Raw!H38 -> 11
A41: Impact of Special Items
A42: Other income (loss) - net Normalised/Adjusted | B42: =Raw!C64 -> 42.3 | C42: =Raw!D64 -> 338.6 | D42: =Raw!E64 -> -236.3 | E42: =Raw!F64 -> -139 | F42: =Raw!G64 -> -87 | G42: =Raw!H64 -> 11 | H42: =H8*H85 -> 0.90685552 | I42: =H42+G42 -> 11.906856 | J42: =J8*$H$85 -> 1.2462652 | K42: =K8*$H$85 -> 1.3210411 | L42: =L8*$H$85 -> 1.4003035 | M42: =M8*$H$85 -> 1.4843217 | N42: =N8*$H$85 -> 1.573381
A44: EBT- Reported | B44: =B33-B36-B40 -> 9449.9 | C44: =C33-C36+C40 -> 8826.8 | D44: =D33-D36+D40 -> 10335.8 | E44: =E33-E36+E40 -> 10364 | F44: =F33-F36+F40 -> 11038 | G44: =G33-G36+G40 -> 2650.8656
A45: EBT- Normalised/Adjusted | B45: =B34-B38-B42 -> 9412.9 | C45: =C34-C38-C42 -> 6815.4 | D45: =D34-D38-D42 -> 10232.2 | E45: =E34-E38-E42 -> 10054 | F45: =F34-F38-F42 -> 10668 | G45: =G34-G38-G42 -> 2494.1089 | H45: =H34-H38+H42 -> 10097.112 | I45: =H45+G45 -> 12591.22 | J45: =J34-J38+J42 -> 13984.711 | K45: =K34-K38+K42 -> 15072.698 | L45: =L34-L38+L42 -> 16224.699 | M45: =M34-M38+M42 -> 17394.398 | N45: =N34-N38+N42 -> 18556.931
A47: Income Tax Expense-Reported | B47: =Raw!C40 -> 1582.7 | C47: =Raw!D40 -> 1648 | D47: =Raw!E40 -> 2053.4 | E47: =Raw!F40 -> 2121 | F47: =Raw!G40 -> 2334 | G47: =Raw!H40 -> 559
A48: Impact of Special Items | B48: =B49-B47 -> 364 | C48: =C49-C47 -> -537 | D48: =D49-D47 -> 0 | E48: =E49-E47 -> 0 | F48: =F49-F47 -> 0 | G48: =G49-G47 -> 0
A49: Income Tax Expense-Normalised/Adjusted | B49: =Raw!C66 -> 1946.7 | C49: =Raw!D66 -> 1111 | D49: =Raw!E66 -> 2053.4 | E49: =Raw!F66 -> 2121 | F49: =Raw!G66 -> 2334 | G49: =Raw!H66 -> 559 | H49: =H45*H89 -> 2060.4493 | I49: =H49+G49 -> 2619.4493 | J49: =J45*$H$89 -> 2853.7653 | K49: =K45*$H$89 -> 3075.7835 | L49: =L45*$H$89 -> 3310.8646 | M49: =M45*$H$89 -> 3549.5571 | N49: =N45*$H$89 -> 3786.7874
A51: Net Income-Reported | B51: =B44-B47 -> 7867.2 | C51: =C44-C47 -> 7178.8 | D51: =D44-D47 -> 8282.4 | E51: =E44-E47 -> 8243 | F51: =F44-F47 -> 8704 | G51: =G44-G47 -> 2091.8656
A52: Net Income-Normalised | B52: =B45-B49 -> 7466.2 | C52: =C45-C49 -> 5704.4 | D52: =D45-D49 -> 8178.8 | E52: =E45-E49 -> 7933 | F52: =F45-F49 -> 8334 | G52: =G45-G49 -> 1935.1089 | H52: =H45-H49 -> 8036.6623 | I52: =H52+G52 -> 9971.7712 | J52: =J45-J49 -> 11130.945 | K52: =K45-K49 -> 11996.914 | L52: =L45-L49 -> 12913.835 | M52: =M45-M49 -> 13844.841 | N52: =N45-N49 -> 14770.143
A54: Share of noncontrolling interests-Reported | B54: 0 | C54: 0 | D54: 0 | E54: 0 | F54: 0 | G54: 0
A55: Impact of Special Items
A56: Share of noncontrolling interests-Normalised/Adjusted | B56: 0 | C56: 0 | D56: 0 | E56: 0 | F56: 0 | G56: 0 | H56: 0 | I56: 0 | J56: 0 | K56: 0 | L56: 0 | M56: 0 | N56: 0
A58: Net Income attributable to shareholders of McDONALD’S CORPORATION - Reported | B58: =B51-B54 -> 7867.2 | C58: =C51-C54 -> 7178.8 | D58: =D51-D54 -> 8282.4 | E58: =E51-E54 -> 8243 | F58: =F51-F54 -> 8704 | G58: =G51-G54 -> 2091.8656
A59: Net Income to shareholders of McDONALD’S CORPORATION - Normalized/Adjusted | B59: =B52-B56 -> 7466.2 | C59: =C52-C56 -> 5704.4 | D59: =D52-D56 -> 8178.8 | E59: =E52-E56 -> 7933 | F59: =F52-F56 -> 8334 | G59: =G52-G56 -> 1935.1089 | H59: =H52-H56 -> 8036.6623 | I59: =H59+G59 -> 9971.7712 | J59: =J52-J56 -> 11130.945 | K59: =K52-K56 -> 11996.914 | L59: =L52-L56 -> 12913.835 | M59: =M52-M56 -> 13844.841 | N59: =N52-N56 -> 14770.143
A61: Equity Dividend | B61: =Raw!C85 -> 3918.6 | C61: =Raw!D85 -> 4168.2 | D61: =Raw!E85 -> 4532.8 | E61: =Raw!F85 -> 4870 | F61: =Raw!G85 -> 5115 | G61: =Raw!H85 -> 1323 | H61: =H59*H93 -> 4984.1805 | I61: =H61+G61 -> 6307.1805 | J61: =J59*$H$93 -> 6903.1942 | K61: =K59*$H$93 -> 7440.2512 | L61: =L59*$H$93 -> 8008.9071 | M61: =M59*$H$93 -> 8586.2988 | N61: =N59*$H$93 -> 9160.1536
A63: Average Shares Outstanding(Basic)
A64: Average Shares Outstanding( Assuming Dilution)
A66: Basic EPS (Normalized) = Adj NI to Shareholders / Basic Shares O/s
A67: Diluted EPS (Normalized) = Adj NI to Shareholders / Diluted Shares O/s
A69: Profitability Ratios (Annual Basis)
A70: Sales Growth (%)-Normalised/Adjusted
A71: Gross Profit Margin (%)-Normalised/Adjusted | B71: =B17/B8 -> 0.60762868 | C71: =C17/C8 -> 0.63242259 | D71: =D17/D8 -> 0.63009685 | E71: =E17/E8 -> 0.6253858 | F71: =F17/F8 -> 0.6335875 | G71: =G17/G8 -> 0.6249769 | H71: =H17/H8 -> 0.62568305 | I71: =I17/I8 -> 0.62552157 | ... N71: =N17/N8 -> 0.62568305
A72: EBITDA Margin (%)-Normalised/Adjusted | B72: =B27/B8 -> 0.53832209 | C72: =C27/C8 -> 0.43935538 | D72: =D27/D8 -> 0.51932046 | E72: =E27/E8 -> 0.51574074 | F72: =F27/F8 -> 0.52891947 | G72: =G27/G8 -> 0.52892043 | H72: =H27/H8 -> 0.5117631 | I72: =I27/I8 -> 0.39473213 | ... N72: =N27/N8 -> 0.5117631
A73: EBIT Margin (%)-Normalised/Adjusted | B73: =B45/B8 -> 0.40532836 | C73: =C45/C8 -> 0.29398773 | D73: =D45/D8 -> 0.40136191 | E73: =E45/E8 -> 0.3878858 | F73: =F45/F8 -> 0.39680119 | G73: =G45/G8 -> 0.38270813 | H73: =H45/H8 -> 0.45935424 | I73: =I45/I8 -> 0.44182666 | ... N73: =N45/N8 -> 0.48658746
A74: Net Income Margin (%)-Normalised/Adjusted | B74: =B52/B8 -> 0.32150162 | C74: =C52/C8 -> 0.24606386 | D74: =D52/D8 -> 0.32081652 | E74: =E52/E8 -> 0.3060571 | F74: =F52/F8 -> 0.30998698 | G74: =G52/G8 -> 0.29693247 | H74: =H52/H8 -> 0.36561693 | I74: =I52/I8 -> 0.34991003 | ... N74: =N52/N8 -> 0.38729285
A75: Net Income attributable to Shareholders Margin (%)-Normalised/Adjusted | B75: =B59/B8 -> 0.32150162 | C75: =C59/C8 -> 0.24606386 | D75: =D59/D8 -> 0.32081652 | E75: =E59/E8 -> 0.3060571 | F75: =F59/F8 -> 0.30998698 | G75: =G59/G8 -> 0.29693247 | H75: =H59/H8 -> 0.36561693 | I75: =I59/I8 -> 0.34991003 | ... N75: =N59/N8 -> 0.38729285
A77: ASSUMPTIONS
A78: Items as % of Net Operating Income (Normalized)
A79: Cost of Goods & Services Sold - Normalized/Adjusted (Other than Dep. Exp) | B79: =B14/B8 -> 0.39237132 | C79: =C14/C8 -> 0.36757741 | D79: =D14/D8 -> 0.36990315 | E79: =E14/E8 -> 0.3746142 | F79: =F14/F8 -> 0.3664125 | G79: =G14/G8 -> 0.3750231 | H79: =AVERAGE(B79:G79) -> 0.37431695
A81: Selling, General & Admin Exp. - Normalized/Adjusted (Excl. Corp. Dep & Amort) | B81: =B21/B8 -> 0.10239031 | C81: =C21/C8 -> 0.10750304 | D81: =D21/D8 -> 0.095521639 | E81: =E21/E8 -> 0.093055556 | F81: =F21/F8 -> 0.096075879 | G81: =G21/G8 -> 0.099432254 | H81: =AVERAGE(B81:G81) -> 0.098996447
A83: Other Cost and Expense, Operating - Normalised/Adjusted | B83: =B25/B8 -> -0.033083723 | C83: =C25/C8 -> 0.085564173 | D83: =D25/D8 -> 0.015254749 | E83: =E25/E8 -> 0.016589506 | F83: =F25/F8 -> 0.0085921518 | G83: =G25/G8 -> -0.0033757864 | H83: =AVERAGE(B83:G83) -> 0.014923512
A85: Non-Op Incomes (Intt Inc + Equity Inc + Other Inc) as % of Net Op Revenue | B85: =B42/B8 -> 0.0018214779 | C85: =C42/C8 -> 0.014605782 | D85: =D42/D8 -> -0.0092689566 | E85: =E42/E8 -> -0.0053626543 | F85: =F42/F8 -> -0.0032360052 | G85: =G42/G8 -> 0.0016878932 | H85: =AVERAGE(B85:G85) -> 4.1256148e-05
A86: Altternatively, Non-Op Incomes (all three) as % of Investments from B/S
A89: Effective Tax Rate - Normalised (%age of EBT - Normalized) | B89: =B49/B45 -> 0.20681193 | C89: =C49/C45 -> 0.16301318 | D89: =D49/D45 -> 0.20068021 | E89: =E49/E45 -> 0.21096081 | F89: =F49/F45 -> 0.21878515 | G89: =G49/G45 -> 0.22412815 | H89: =AVERAGE(B89:G89) -> 0.20406324
A91: Share of Non-Controlling Int. - Norm./Adj. (%age of NI - Normalized/Adjusted) | B91: =B56/B52 -> 0 | C91: =C56/C52 -> 0 | D91: =D56/D52 -> 0 | E91: =E56/E52 -> 0 | F91: =F56/F52 -> 0 | G91: =G56/G52 -> 0 | H91: =AVERAGE(B91:G91) -> 0
A93: Dividend Payout Ratio (ie., Dividend / NI attributable to Shareholders-Normalized) | B93: =B61/B59 -> 0.5248453 | C93: =C61/C59 -> 0.73069911 | D93: =D61/D59 -> 0.55421333 | E93: =E61/E59 -> 0.61389134 | F93: =F61/F59 -> 0.6137509 | G93: =G61/G59 -> 0.68368246 | H93: =AVERAGE(B93:G93) -> 0.62018041
A95: Share-based Compensation Expenses | B95: =Raw!C84 -> 139.2 | C95: =Raw!D84 -> 166.7 | D95: =Raw!E84 -> 175.2 | E95: =Raw!F84 -> 172 | F95: =Raw!G84 -> 165 | G95: =Raw!H84 -> 60 | H95: =(H14+H21)*H96 -> 154.11794 | I95: =H95+G95 -> 214.11794 | J95: =(J14+J21)*$H$96 -> 211.7998 | K95: =(K14+K21)*$H$96 -> 224.50778 | L95: =(L14+L21)*$H$96 -> 237.97825 | M95: =(M14+M21)*$H$96 -> 252.25695 | N95: =(N14+N21)*$H$96 -> 267.39236
A96: Share-based Compensation as %age of SG&A+COGS - Normalized/Adjusted | B96: =B95/(B14+B21) -> 0.012115093 | C96: =C95/(C14+C21) -> 0.015135832 | D96: =D95/(D14+D21) -> 0.014765621 | E96: =E95/(E14+E21) -> 0.014189078 | F96: =F95/(F14+F21) -> 0.013270066 | G96: =G95/(G14+G21) -> 0.019404756 | H96: =AVERAGE(B96:G96) -> 0.014813408

Sheet McD-BS
A1: McDONALD’S CORPORATION
A2: (in USD million except per Share Data)
A3: Balance Sheet | B3: 12 | C3: 12 | D3: 12 | E3: 12 | F3: 12 | G3: 3 | H3: 9 | I3: 12 | J3: 12 | K3: 12 | L3: 12 | M3: 12
B4: 44561 | C4: 44926 | D4: 45291 | E4: 45657 | F4: 46022 | G4: 46112 | H4: 46387 | I4: 46752 | J4: 47118 | K4: 47483 | L4: 47848 | M4: 48213
A6: Current Assets
A7: Cash and cash equivalents | B7: =Raw!C91 -> 4709.2 | C7: =Raw!D91 -> 2583.8 | D7: =Raw!E91 -> 4579.3 | E7: =Raw!F91 -> 1085 | F7: =Raw!G91 -> 774 | G7: =Raw!H91 -> 1170 | H7: ='McD-CFS'!H28 -> 3645.6943 | I7: ='McD-CFS'!I28 -> 3738.8673 | J7: ='McD-CFS'!J28 -> 2088.4862 | K7: ='McD-CFS'!K28 -> 2204.5804 | L7: ='McD-CFS'!L28 -> 3186.2444 | M7: ='McD-CFS'!M28 -> 7412.6227
A8: Total Cash, Cash equivalents & Short term investments | B8: =Raw!C92 -> 4709.2 | C8: =Raw!D92 -> 2583.8 | D8: =Raw!E92 -> 4579.3 | E8: =Raw!F92 -> 1085 | F8: =Raw!G92 -> 774 | G8: =Raw!H92 -> 1170 | H8: =H7 -> 3645.6943 | I8: =I7 -> 3738.8673 | J8: =J7 -> 2088.4862 | K8: =K7 -> 2204.5804 | L8: =L7 -> 3186.2444 | M8: =M7 -> 7412.6227
A9: Accounts and notes receivable | B9: =Raw!C93 -> 1872.4 | C9: =Raw!D93 -> 2115 | D9: =Raw!E93 -> 2488 | E9: =Raw!F93 -> 2383 | F9: =Raw!G93 -> 2466 | G9: =Raw!H93 -> 2432 | H9: =H56 -> 2653.7836 | I9: =I56 -> 2813.0107 | J9: =J56 -> 2981.7913 | K9: =K56 -> 3160.6988 | L9: =L56 -> 3350.3407 | M9: =M56 -> 3551.3611
A10: Inventories | B10: =Raw!C94 -> 55.6 | C10: =Raw!D94 -> 52 | D10: =Raw!E94 -> 52.8 | E10: =Raw!F94 -> 56 | F10: =Raw!G94 -> 61 | G10: =Raw!H94 -> 61 | H10: =H58 -> 63.525 | I10: =I58 -> 67.307463 | J10: =J58 -> 71.345911 | K10: =K58 -> 75.626666 | L10: =L58 -> 80.164266 | M10: =M58 -> 84.974121
A11: Prepaid expenses and other current assets | B11: =Raw!C95 -> 511.3 | C11: =Raw!D95 -> 673.4 | D11: =Raw!E95 -> 866.3 | E11: =Raw!F95 -> 1074 | F11: =Raw!G95 -> 863 | G11: =Raw!H95 -> 1046 | H11: =H60 -> 903.65837 | I11: =I60 -> 957.87788 | J11: =J60 -> 1015.3505 | K11: =K60 -> 1076.2716 | L11: =L60 -> 1140.8479 | M11: =M60 -> 1209.2987
A12: Total Current assets | B12: =SUM(B8:B11) -> 7148.5 | C12: =SUM(C8:C11) -> 5424.2 | D12: =SUM(D8:D11) -> 7986.4 | E12: =SUM(E8:E11) -> 4598 | F12: =SUM(F8:F11) -> 4164 | G12: =SUM(G8:G11) -> 4709 | H12: =SUM(H8:H11) -> 7266.6613 | I12: =SUM(I8:I11) -> 7577.0633 | ... M12: =SUM(M8:M11) -> 12258.257
A13: Investments in and advances to affiliates | B13: =Raw!C97 -> 1201.2 | C13: =Raw!D97 -> 1064.5 | D13: =Raw!E97 -> 1080.2 | E13: =Raw!F97 -> 2710 | F13: =Raw!G97 -> 2820 | G13: =Raw!H97 -> 2865 | H13: =G13 -> 2865 | I13: =H13 -> 2865 | J13: =I13 -> 2865 | K13: =J13 -> 2865 | L13: =K13 -> 2865 | M13: =L13 -> 2865
A14: PPE-Net property and equipment | B14: =Raw!C98 -> 24720.6 | C14: =Raw!D98 -> 23773.6 | D14: =Raw!E98 -> 24907.6 | E14: =Raw!F98 -> 25295 | F14: =Raw!G98 -> 28241 | G14: =Raw!H98 -> 28245 | H14: ='Fixed Assets Schedule'!H10 -> 29009.047 | I14: ='Fixed Assets Schedule'!I10 -> 30009.011 | J14: ='Fixed Assets Schedule'!J10 -> 31120.947 | K14: ='Fixed Assets Schedule'!K10 -> 32347.925 | L14: ='Fixed Assets Schedule'!L10 -> 33693.456 | M14: ='Fixed Assets Schedule'!M10 -> 35161.501
A15: Goodwill | B15: =Raw!C99 -> 2782.5 | C15: =Raw!D99 -> 2900.4 | D15: =Raw!E99 -> 3040.4 | E15: =Raw!F99 -> 3145 | F15: =Raw!G99 -> 3354 | G15: =Raw!H99 -> 3349 | H15: =G15 -> 3349 | I15: =H15 -> 3349 | J15: =I15 -> 3349 | K15: =J15 -> 3349 | L15: =K15 -> 3349 | M15: =L15 -> 3349
A16: Other Non-Current Assets | B16: =Raw!C100 -> 18001.5 | C16: =Raw!D100 -> 17272.9 | D16: =Raw!E100 -> 19132.2 | E16: =Raw!F100+2 -> 19436 | F16: =Raw!G100+1 -> 20938 | G16: =Raw!H100+1 -> 20871 | H16: =G16 -> 20871 | I16: =H16 -> 20871 | J16: =I16 -> 20871 | K16: =J16 -> 20871 | L16: =K16 -> 20871 | M16: =L16 -> 20871
A17: Other Intangible Assets | B17: =Raw!C101 -> 0 | C17: =Raw!D101 -> 0 | D17: =Raw!E101 -> 0 | E17: =Raw!F101 -> 0 | F17: =Raw!G101 -> 0 | G17: =Raw!H101 -> 0 | H17: 0 | I17: 0 | J17: 0 | K17: 0 | L17: 0 | M17: 0
A18: Total Assets | B18: =SUM(B12:B17) -> 53854.3 | C18: =SUM(C12:C17) -> 50435.6 | D18: =SUM(D12:D17) -> 56146.8 | E18: =SUM(E12:E17) -> 55184 | F18: =SUM(F12:F17) -> 59517 | G18: =SUM(G12:G17) -> 60039 | H18: =SUM(H12:H17) -> 63360.708 | I18: =SUM(I12:I17) -> 64671.074 | ... M18: =SUM(M12:M17) -> 74504.757
A20: Current Liabilities
A21: Accounts payable and accrued expenses | B21: =Raw!C105 -> 1006.8 | C21: =Raw!D105 -> 980.2 | D21: =Raw!E105 -> 1102.9 | E21: =Raw!F105 -> 1029 | F21: =Raw!G105 -> 1149 | G21: =Raw!H105 -> 1091 | H21: =H64 -> 1206.1085 | I21: =I64 -> 1277.9237 | J21: =J64 -> 1354.5992 | K21: =K64 -> 1435.8751 | L21: =L64 -> 1522.0276 | M21: =M64 -> 1613.3493
A22: Accrued Interest | B22: =Raw!C106 -> 363.3 | C22: =Raw!D106 -> 393.4 | D22: =Raw!E106 -> 468.9 | E22: =Raw!F106 -> 482 | F22: =Raw!G106 -> 533 | G22: =Raw!H106 -> 448 | H22: =G22 -> 448 | I22: =H22 -> 448 | J22: =I22 -> 448 | K22: =J22 -> 448 | L22: =K22 -> 448 | M22: =L22 -> 448
A23: Accrued Payroll & Other Liabilities | B23: =Raw!C107 -> 1347 | C23: =Raw!D107 -> 1237.4 | D23: =Raw!E107 -> 1433.6 | E23: =Raw!F107 -> 1129 | F23: =Raw!G107 -> 1488 | G23: =Raw!H107 -> 1257 | H23: =G23 -> 1257 | I23: =H23 -> 1257 | J23: =I23 -> 1257 | K23: =J23 -> 1257 | L23: =K23 -> 1257 | M23: =L23 -> 1257
A24: Short term borrowings & Current maturities of long-term debt | B24: =Raw!C108 -> 0 | C24: =Raw!D108 -> 0 | D24: =Raw!E108 -> 2192.4 | E24: =Raw!F108 -> 0 | F24: =Raw!G108 -> 0 | G24: =Raw!H108 -> 0 | H24: ='Debt Schedule'!H9 -> 3201 | I24: ='Debt Schedule'!I9 -> 5166 | J24: ='Debt Schedule'!J9 -> 3637 | K24: ='Debt Schedule'!K9 -> 3011 | L24: ='Debt Schedule'!L9 -> 0 | M24: ='Debt Schedule'!M9 -> 0
A25: Accrued income taxes | B25: =Raw!C109 -> 360.7 | C25: =Raw!D109 -> 274.9 | D25: =Raw!E109 -> 705.1 | E25: =Raw!F109 -> 361 | F25: =Raw!G109 -> 250 | G25: =Raw!H109 -> 391 | H25: =G25 -> 391 | I25: =H25 -> 391 | J25: =I25 -> 391 | K25: =J25 -> 391 | L25: =K25 -> 391 | M25: =L25 -> 391
A26: Other taxes | B26: =Raw!C110 -> 236.7 | C26: =Raw!D110 -> 255.1 | D26: =Raw!E110 -> 268 | E26: =Raw!F110 -> 224 | F26: =Raw!G110 -> 247 | G26: =Raw!H110 -> 253 | H26: =G26 -> 253 | I26: =H26 -> 253 | J26: =I26 -> 253 | K26: =J26 -> 253 | L26: =K26 -> 253 | M26: =L26 -> 253
A27: Lease liability | B27: =Raw!C111 -> 705.5 | C27: =Raw!D111 -> 661.1 | D27: =Raw!E111 -> 688.1 | E27: =Raw!F111 -> 636 | F27: =Raw!G111 -> 694 | G27: =Raw!H111 -> 707 | H27: =G27 -> 707 | I27: =H27 -> 707 | J27: =I27 -> 707 | K27: =J27 -> 707 | L27: =K27 -> 707 | M27: =L27 -> 707
A29: Total Current Liabilities | B29: =SUM(B21:B27) -> 4020 | C29: =SUM(C21:C27) -> 3802.1 | D29: =SUM(D21:D27) -> 6859 | E29: =SUM(E21:E27) -> 3861 | F29: =SUM(F21:F27) -> 4361 | G29: =SUM(G21:G27) -> 4147 | H29: =SUM(H21:H27) -> 7463.1085 | I29: =SUM(I21:I27) -> 9499.9237 | ... M29: =SUM(M21:M27) -> 4669.3493
A31: Long term Debt | B31: =Raw!C113 -> 35622.7 | C31: =Raw!D113 -> 35903.5 | D31: =Raw!E113 -> 37152.9 | E31: =Raw!F113 -> 38424 | F31: =Raw!G113 -> 39973 | G31: =Raw!H113 -> 40105 | H31: ='Debt Schedule'!H10 -> 36904 | I31: ='Debt Schedule'!I10 -> 31738 | J31: ='Debt Schedule'!J10 -> 28101 | K31: ='Debt Schedule'!K10 -> 25090 | L31: ='Debt Schedule'!L10 -> 25090 | M31: ='Debt Schedule'!M10 -> 25090
A32: Long-term lease liability | B32: =Raw!C114 -> 13020.9 | C32: =Raw!D114 -> 12134.4 | D32: =Raw!E114 -> 13057.7 | E32: =Raw!F114 -> 12888 | F32: =Raw!G114 -> 14147 | G32: =Raw!H114 -> 14069 | H32: =G32 -> 14069 | I32: =H32 -> 14069 | J32: =I32 -> 14069 | K32: =J32 -> 14069 | L32: =K32 -> 14069 | M32: =L32 -> 14069
A33: Long-term income taxes | B33: =Raw!C115 -> 1896.8 | C33: =Raw!D115 -> 791.9 | D33: =Raw!E115 -> 363.2 | E33: =Raw!F115 -> 344 | F33: =Raw!G115 -> 139 | G33: =Raw!H115 -> 151 | H33: =G33 -> 151 | I33: =H33 -> 151 | J33: =I33 -> 151 | K33: =J33 -> 151 | L33: =K33 -> 151 | M33: =L33 -> 151
A34: Deferred Income Taxes | B34: =Raw!C116 -> 2075.6 | C34: =Raw!D116 -> 1997.5 | D34: =Raw!E116 -> 1680.9 | E34: =Raw!F116 -> 1914 | F34: =Raw!G116 -> 1038 | G34: =Raw!H116 -> 1220 | H34: =G34 -> 1220 | I34: =H34 -> 1220 | J34: =I34 -> 1220 | K34: =J34 -> 1220 | L34: =K34 -> 1220 | M34: =L34 -> 1220
A35: Deferred revenues - initial franchise fees | B35: =Raw!C117 -> 738.3 | C35: =Raw!D117 -> 757.8 | D35: =Raw!E117 -> 790.1 | E35: =Raw!F117 -> 778 | F35: =Raw!G117 -> 945 | G35: =Raw!H117 -> 946 | H35: =G35 -> 946 | I35: =H35 -> 946 | J35: =I35 -> 946 | K35: =J35 -> 946 | L35: =K35 -> 946 | M35: =L35 -> 946
A36: Other long-term Liabilities | B36: =Raw!C118 -> 1081 | C36: =Raw!D118 -> 1051.8 | D36: =Raw!E118 -> 949.7 | E36: =Raw!F118 -> 771 | F36: =Raw!G118 -> 704 | G36: =Raw!H118 -> 686 | H36: =G36 -> 686 | I36: =H36 -> 686 | J36: =I36 -> 686 | K36: =J36 -> 686 | L36: =K36 -> 686 | M36: =L36 -> 686
A37: Total Liabilities | B37: =SUM(B29:B36) -> 58455.3 | C37: =SUM(C29:C36) -> 56439 | D37: =SUM(D29:D36) -> 60853.5 | E37: =SUM(E29:E36) -> 58980 | F37: =SUM(F29:F36) -> 61307 | G37: =SUM(G29:G36) -> 61324 | H37: =SUM(H29:H36) -> 61439.109 | I37: =SUM(I29:I36) -> 58309.924 | ... M37: =SUM(M29:M36) -> 46831.349
A39: McDONALD’S CORPORATION Shareholders' Equity
A40: Common stock, $0.01 par value | B40: =Raw!C122 -> 16.6 | C40: =Raw!D122 -> 16.6 | D40: =Raw!E122 -> 16.6 | E40: =Raw!F122 -> 17 | F40: =Raw!G122 -> 17 | G40: =Raw!H122 -> 17 | H40: =G40 -> 17 | I40: =H40 -> 17 | J40: =I40 -> 17 | K40: =J40 -> 17 | L40: =K40 -> 17 | M40: =L40 -> 17
A41: Capital surplus | B41: =Raw!C123 -> 8231.6 | C41: =Raw!D123 -> 8547.1 | D41: =Raw!E123 -> 8892.9 | E41: =Raw!F123 -> 9281 | F41: =Raw!G123 -> 9641 | G41: =Raw!H123 -> 9792 | H41: =G41+'McD IS'!H95 -> 9946.1179 | I41: =H41+'McD IS'!J95 -> 10157.918 | J41: =I41+'McD IS'!K95 -> 10382.426 | K41: =J41+'McD IS'!L95 -> 10620.404 | L41: =K41+'McD IS'!M95 -> 10872.661 | M41: =L41+'McD IS'!N95 -> 11140.053
A42: Reinvested earnings | B42: =Raw!C124 -> 57534.7 | C42: =Raw!D124 -> 59543.9 | D42: =Raw!E124 -> 63479.9 | E42: =Raw!F124 -> 66834 | F42: =Raw!G124 -> 70282 | G42: =Raw!H124 -> 70942 | H42: =G42+('McD IS'!H59-'McD IS'!H61) -> 73994.482 | I42: =H42+('McD IS'!J59-'McD IS'!J61) -> 78222.233 | J42: =I42+('McD IS'!K59-'McD IS'!K61) -> 82778.896 | K42: =J42+('McD IS'!L59-'McD IS'!L61) -> 87683.823 | L42: =K42+('McD IS'!M59-'McD IS'!M61) -> 92942.365 | M42: =L42+('McD IS'!N59-'McD IS'!N61) -> 98552.355
A43: Accumulated other comprehensive income (loss) | B43: =Raw!C125 -> -2573.7 | C43: =Raw!D125 -> -2486.6 | D43: =Raw!E125 -> -2456 | E43: =Raw!F125 -> -2553 | F43: =Raw!G125 -> -2414 | G43: =Raw!H125 -> -2363 | H43: =G43 -> -2363 | I43: =H43 -> -2363 | J43: =I43 -> -2363 | K43: =J43 -> -2363 | L43: =K43 -> -2363 | M43: =L43 -> -2363
A44: Treasury stock, (shares bought by the company) ,at cost | B44: =Raw!C126 -> -67810.2 | C44: =Raw!D126 -> -71624.4 | D44: =Raw!E126 -> -74640.1 | E44: =Raw!F126 -> -77375 | F44: =Raw!G126 -> -79316 | G44: =Raw!H126 -> -79673 | H44: =G44 -> -79673 | I44: =H44 -> -79673 | J44: =I44 -> -79673 | K44: =J44 -> -79673 | L44: =K44 -> -79673 | M44: =L44 -> -79673
A45: Equity Attributable to Shreholders' of McDONALD’S CORPORATION | B45: =SUM(B40:B44) -> -4601 | C45: =SUM(C40:C44) -> -6003.4 | D45: =SUM(D40:D44) -> -4706.7 | E45: =SUM(E40:E44) -> -3796 | F45: =SUM(F40:F44) -> -1790 | G45: =SUM(G40:G44) -> -1285 | H45: =SUM(H40:H44) -> 1921.5997 | I45: =SUM(I40:I44) -> 6361.1506 | ... M45: =SUM(M40:M44) -> 27673.408
A46: Equity Attributable to non-controlling interests | B46: 0 | C46: 0 | D46: 0 | E46: 0 | F46: 0 | G46: 0 | H46: 0 | I46: 0 | J46: 0 | K46: 0 | L46: 0 | M46: 0
A47: Total Equity | B47: =B45+B46 -> -4601 | C47: =C45+C46 -> -6003.4 | D47: =D45+D46 -> -4706.7 | E47: =E45+E46 -> -3796 | F47: =F45+F46 -> -1790 | G47: =G45+G46 -> -1285 | H47: =H45+H46 -> 1921.5997 | I47: =I45+I46 -> 6361.1506 | ... M47: =M45+M46 -> 27673.408
A49: Total Liabilities & Equity | B49: =B37+B47 -> 53854.3 | C49: =C37+C47 -> 50435.6 | D49: =D37+D47 -> 56146.8 | E49: =E37+E47 -> 55184 | F49: =F37+F47 -> 59517 | G49: =G37+G47 -> 60039 | H49: =H37+H47 -> 63360.708 | I49: =I37+I47 -> 64671.074 | ... M49: =M37+M47 -> 74504.757
A51: Check | B51: =B18-B49 -> 0 | C51: =C18-C49 -> 0 | D51: =D18-D49 -> 0 | E51: =E18-E49 -> 0 | F51: =F18-F49 -> 0 | G51: =G18-G49 -> 0 | H51: =H18-H49 -> 0 | I51: =I18-I49 -> 0 | ... M51: =M18-M49 -> 0
A54: Working Capital
A55: Operating Current Assets
A56: Trade accounts receivable | B56: =B9 -> 1872.4 | C56: =C9 -> 2115 | D56: =D9 -> 2488 | E56: =E9 -> 2383 | F56: =F9 -> 2466 | G56: =G9 -> 2432 | H56: =$H$57*'McD IS'!I8/365 -> 2653.7836 | I56: =$H$57*'McD IS'!J8/365 -> 2813.0107 | J56: =$H$57*'McD IS'!K8/365 -> 2981.7913 | K56: =$H$57*'McD IS'!L8/365 -> 3160.6988 | L56: =$H$57*'McD IS'!M8/365 -> 3350.3407 | M56: =$H$57*'McD IS'!N8/365 -> 3551.3611
A57: Receivable Days | B57: =(365*B56)/'McD IS'!B8 -> 29.428969 | C57: =(365*C56)/'McD IS'!C8 -> 33.299759 | D57: =(365*D56)/'McD IS'!D8 -> 35.62135 | E57: =(365*E56)/'McD IS'!E8 -> 33.556906 | F57: =(365*F56)/'McD IS'!F8 -> 33.479264 | G57: =((G4-F4)*G56)/'McD IS'!G8 -> 33.586006 | H57: =AVERAGE(C57:F57) -> 33.98932
A58: Inventories | B58: =B10 -> 55.6 | C58: =C10 -> 52 | D58: =D10 -> 52.8 | E58: =E10 -> 56 | F58: =F10 -> 61 | G58: =G10 -> 61 | H58: =($H$59*'McD IS'!I14)/365 -> 63.525 | I58: =($H$59*'McD IS'!J14)/365 -> 67.307463 | J58: =($H$59*'McD IS'!K14)/365 -> 71.345911 | K58: =($H$59*'McD IS'!L14)/365 -> 75.626666 | L58: =($H$59*'McD IS'!M14)/365 -> 80.164266 | M58: =($H$59*'McD IS'!N14)/365 -> 84.974121
A59: Inventory Days | B59: =(365*B58)/'McD IS'!B14 -> 2.227173 | C59: =(365*C58)/'McD IS'!C14 -> 2.2273335 | D59: =(365*D58)/'McD IS'!D14 -> 2.043647 | E59: =(365*E58)/'McD IS'!E14 -> 2.1050463 | F59: =(365*F58)/'McD IS'!F14 -> 2.2601766 | G59: =((G4-F4)*G58)/'McD IS'!G14 -> 2.246294 | H59: =AVERAGE(B59:F59) -> 2.1726753
A60: Prepaid expenses and other current assets | B60: =B11 -> 511.3 | C60: =C11 -> 673.4 | D60: =D11 -> 866.3 | E60: =E11 -> 1074 | F60: =F11 -> 863 | G60: =G11 -> 1046 | H60: =$H$61*'McD IS'!I8 -> 903.65837 | I60: =$H$61*'McD IS'!J8 -> 957.87788 | J60: =$H$61*'McD IS'!K8 -> 1015.3505 | K60: =$H$61*'McD IS'!L8 -> 1076.2716 | L60: =$H$61*'McD IS'!M8 -> 1140.8479 | M60: =$H$61*'McD IS'!N8 -> 1209.2987
A61: %age of Sales | B61: =B60/'McD IS'!B8 -> 0.022017061 | C61: =C60/'McD IS'!C8 -> 0.029047648 | D61: =D60/'McD IS'!D8 -> 0.033980944 | E61: =E60/'McD IS'!E8 -> 0.041435185 | F61: =F60/'McD IS'!F8 -> 0.032099684 | G61: =G60/'McD IS'!G8 -> 0.1605033 | H61: =AVERAGE(C61, D61, F61) -> 0.031709425
A63: Operating Current Liabilities
A64: =A21 -> Accounts payable and accrued expenses | B64: =B21 -> 1006.8 | C64: =C21 -> 980.2 | D64: =D21 -> 1102.9 | E64: =E21 -> 1029 | F64: =F21 -> 1149 | G64: =G21 -> 1091 | H64: =($H$65*'McD IS'!I14)/365 -> 1206.1085 | I64: =($H$65*'McD IS'!J14)/365 -> 1277.9237 | J64: =($H$65*'McD IS'!K14)/365 -> 1354.5992 | K64: =($H$65*'McD IS'!L14)/365 -> 1435.8751 | L64: =($H$65*'McD IS'!M14)/365 -> 1522.0276 | M64: =($H$65*'McD IS'!N14)/365 -> 1613.3493
A65: Payable Days | B65: =(365*B64)/'McD IS'!B14 -> 40.329456 | C65: =(365*C64)/'McD IS'!C14 -> 41.985237 | D65: =(365*D64)/'McD IS'!D14 -> 42.688225 | E65: =(365*E64)/'McD IS'!E14 -> 38.680227 | F65: =(365*F64)/'McD IS'!F14 -> 42.572835 | G65: =((G4-F4)*G64)/'McD IS'!G14 -> 40.175521 | H65: =AVERAGE(B65:F65) -> 41.251196
A67: Net Working Capital (CA-CL) | B67: =B56+B58+B60-B64 -> 1432.5 | C67: =C56+C58+C60-C64 -> 1860.2 | D67: =D56+D58+D60-D64 -> 2304.2 | E67: =E56+E58+E60-E64 -> 2484 | F67: =F56+F58+F60-F64 -> 2241 | G67: =G56+G58+G60-G64 -> 2448 | H67: =H56+H58+H60-H64 -> 2414.8585 | I67: =I56+I58+I60-I64 -> 2560.2723 | ... M67: =M56+M58+M60-M64 -> 3232.2847
A68: Change in NWC (CY-PY) | C68: =C67-B67 -> 427.7 | D68: =D67-C67 -> 444 | E68: =E67-D67 -> 179.8 | F68: =F67-E67 -> -243 | G68: =G67-F67 -> 207 | H68: =H67-G67 -> -33.14153 | I68: =I67-H67 -> 145.41378 | J68: =J67-I67 -> 153.61634 | ... M68: =M67-L67 -> 182.95951
A70: Cash Conversion Cycle | B70: =B57+B59-B65 -> -8.6733139 | C70: =C57+C59-C65 -> -6.4581443 | D70: =D57+D59-D65 -> -5.0232285 | E70: =E57+E59-E65 -> -3.0182744 | F70: =F57+F59-F65 -> -6.8333951 | G70: =G57+G59-G65 -> -4.3432215

Sheet McD-CFS
A1: McDONALD’S CORPORATION
A2: (in USD million except per Share Data)
A3: Cash Flow Statement | H3: 9 | I3: 12 | J3: 12 | K3: 12 | L3: 12 | M3: 12
H4: 46387 | I4: 46752 | J4: 47118 | K4: 47483 | L4: 47848 | M4: 48213
A6: Cash From Operating Activities
A7: Net Income (Consolidated) | H7: ='McD IS'!H52 -> 8036.6623 | I7: ='McD IS'!J52 -> 11130.945 | J7: ='McD IS'!K52 -> 11996.914 | K7: ='McD IS'!L52 -> 12913.835 | L7: ='McD IS'!M52 -> 13844.841 | M7: ='McD IS'!N52 -> 14770.143
A8: Add: Depreciation and amortization | H8: ='Fixed Assets Schedule'!H9 -> 1611.7207 | I8: ='Fixed Assets Schedule'!I9 -> 2264.9842 | J8: ='Fixed Assets Schedule'!J9 -> 2348.9096 | K8: ='Fixed Assets Schedule'!K9 -> 2441.518 | L8: ='Fixed Assets Schedule'!L9 -> 2543.0744 | M8: ='Fixed Assets Schedule'!M9 -> 2653.8777
A9: Add: Share-based compensation expense | H9: ='McD IS'!H95 -> 154.11794 | I9: ='McD IS'!J95 -> 211.7998 | J9: ='McD IS'!K95 -> 224.50778 | K9: ='McD IS'!L95 -> 237.97825 | L9: ='McD IS'!M95 -> 252.25695 | M9: ='McD IS'!N95 -> 267.39236
A10: Add: Interest Expense | H10: ='Debt Schedule'!H13 -> 1152.9111 | I10: ='Debt Schedule'!I13 -> 1475.868 | J10: ='Debt Schedule'!J13 -> 1315.5155 | K10: ='Debt Schedule'!K13 -> 1146.8071 | L10: ='Debt Schedule'!L13 -> 1019.399 | M10: ='Debt Schedule'!M13 -> 961.69354
A11: Minus: Changes in NWC | H11: =-'McD-BS'!H68 -> 33.14153 | I11: =-'McD-BS'!I68 -> -145.41378 | J11: =-'McD-BS'!J68 -> -153.61634 | K11: =-'McD-BS'!K68 -> -162.83332 | L11: =-'McD-BS'!L68 -> -172.60331 | M11: =-'McD-BS'!M68 -> -182.95951
A12: Net Cash Provided by Operating Activities | H12: =SUM(H7:H11) -> 10988.554 | I12: =SUM(I7:I11) -> 14938.184 | J12: =SUM(J7:J11) -> 15732.231 | K12: =SUM(K7:K11) -> 16577.305 | L12: =SUM(L7:L11) -> 17486.968 | M12: =SUM(M7:M11) -> 18470.148
A14: Cash From Investing Activities
A15: Capital Expenditure | H15: =-'Fixed Assets Schedule'!H7 -> -2375.7677 | I15: =-'Fixed Assets Schedule'!I7 -> -3264.9484 | J15: =-'Fixed Assets Schedule'!J7 -> -3460.8453 | K15: =-'Fixed Assets Schedule'!K7 -> -3668.496 | L15: =-'Fixed Assets Schedule'!L7 -> -3888.6058 | M15: =-'Fixed Assets Schedule'!M7 -> -4121.9221
A17: Net Cash Used for Investing Activities | H17: =H15 -> -2375.7677 | I17: =I15 -> -3264.9484 | J17: =J15 -> -3460.8453 | K17: =K15 -> -3668.496 | L17: =L15 -> -3888.6058 | M17: =M15 -> -4121.9221
A19: Cash From Financing Activities
A20: Cash dividends paid | H20: =-'McD IS'!H61 -> -4984.1805 | I20: =-'McD IS'!J61 -> -6903.1942 | J20: =-'McD IS'!K61 -> -7440.2512 | K20: =-'McD IS'!L61 -> -8008.9071 | L20: =-'McD IS'!M61 -> -8586.2988 | M20: =-'McD IS'!N61 -> -9160.1536
A21: Debt Raised | H21: ='Debt Schedule'!H7 -> 0 | I21: ='Debt Schedule'!I7 -> 0 | J21: ='Debt Schedule'!J7 -> 0 | K21: ='Debt Schedule'!K7 -> 0 | L21: ='Debt Schedule'!L7 -> 0 | M21: ='Debt Schedule'!M7 -> 0
A22: Debt Repaid | H22: =-'Debt Schedule'!H6 -> 0 | I22: =-'Debt Schedule'!I6 -> -3201 | J22: =-'Debt Schedule'!J6 -> -5166 | K22: =-'Debt Schedule'!K6 -> -3637 | L22: =-'Debt Schedule'!L6 -> -3011 | M22: =-'Debt Schedule'!M6 -> 0
A23: Interest Expense | H23: =-'Debt Schedule'!H13 -> -1152.9111 | I23: =-'Debt Schedule'!I13 -> -1475.868 | J23: =-'Debt Schedule'!J13 -> -1315.5155 | K23: =-'Debt Schedule'!K13 -> -1146.8071 | L23: =-'Debt Schedule'!L13 -> -1019.399 | M23: =-'Debt Schedule'!M13 -> -961.69354
A24: Net Cash Provided by/(Used for) Financing Activities | H24: =SUM(H20:H23) -> -6137.0916 | I24: =SUM(I20:I23) -> -11580.062 | J24: =SUM(J20:J23) -> -13921.767 | K24: =SUM(K20:K23) -> -12792.714 | L24: =SUM(L20:L23) -> -12616.698 | M24: =SUM(M20:M23) -> -10121.847
A26: Net Increase/(Decrease) in Cash and Cash Equivalents | H26: =SUM(H12,H17,H24) -> 2475.6943 | I26: =SUM(I12,I17,I24) -> 93.172992 | J26: =SUM(J12,J17,J24) -> -1650.3811 | K26: =SUM(K12,K17,K24) -> 116.09426 | L26: =SUM(L12,L17,L24) -> 981.66394 | M26: =SUM(M12,M17,M24) -> 4226.3783
A27: Cash and Cash Equivalents, Beginning of Year | H27: ='McD-BS'!G7 -> 1170 | I27: =H28 -> 3645.6943 | J27: =I28 -> 3738.8673 | K27: =J28 -> 2088.4862 | L27: =K28 -> 2204.5804 | M27: =L28 -> 3186.2444
A28: Cash and Cash Equivalents, End of Period | H28: =SUM(H26,H27) -> 3645.6943 | I28: =SUM(I26,I27) -> 3738.8673 | J28: =SUM(J26,J27) -> 2088.4862 | K28: =SUM(K26,K27) -> 2204.5804 | L28: =SUM(L26,L27) -> 3186.2444 | M28: =SUM(M26,M27) -> 7412.6227

Sheet Debt Schedule
A1: McDONALD’S CORPORATION
A2: (in USD million except per Share Data)
A3: Debt Schedule | H3: 9 | I3: 12 | J3: 12 | K3: 12 | L3: 12 | M3: 12
H4: 46387 | I4: 46752 | J4: 47118 | K4: 47483 | L4: 47848 | M4: 48213
A5: Opening Debt | H5: ='McD-BS'!G31+'McD-BS'!G24 -> 40105 | I5: =H8 -> 40105 | J5: =I8 -> 36904 | K5: =J8 -> 31738 | L5: =K8 -> 28101 | M5: =L8 -> 25090
A6: Less: Mandatory Debt Repayments | H6: 0 | I6: =Raw!D150 -> 3201 | J6: =Raw!E150 -> 5166 | K6: =Raw!F150 -> 3637 | L6: =Raw!G150 -> 3011 | M6: =Raw!H150 -> 0
A7: Add: debt raised | H7: 0 | I7: 0 | J7: 0 | K7: 0 | L7: 0 | M7: 0
A8: Closing Total Debt | H8: =H5-H6+H7 -> 40105 | I8: =I5-I6+I7 -> 36904 | J8: =J5-J6+J7 -> 31738 | K8: =K5-K6+K7 -> 28101 | L8: =L5-L6+L7 -> 25090 | M8: =M5-M6+M7 -> 25090
A9: Current portion of long term debt | H9: =I6 -> 3201 | I9: =J6 -> 5166 | J9: =K6 -> 3637 | K9: =L6 -> 3011 | L9: 0 | M9: 0
A10: Long term debt + Short Term Debt | H10: =H8-H9 -> 36904 | I10: =I8-I9 -> 31738 | J10: =J8-J9 -> 28101 | K10: =K8-K9 -> 25090 | L10: =L8-L9 -> 25090 | M10: =M8-M9 -> 25090
A13: Interest Expense | H13: =H15*AVERAGE(H5,H8)*0.75 -> 1152.9111 | I13: =$H$15*AVERAGE(I5,I8) -> 1475.868 | J13: =$H$15*AVERAGE(J5,J8) -> 1315.5155 | K13: =$H$15*AVERAGE(K5,K8) -> 1146.8071 | L13: =$H$15*AVERAGE(L5,L8) -> 1019.399 | M13: =$H$15*AVERAGE(M5,M8) -> 961.69354
A15: Average Interest Rate | H15: =Raw!F146 -> 0.038329755

Sheet Fixed Assets Schedule
A1: McDONALD’S CORPORATION
A2: (in USD million except per Share Data)
A3: Property, Plant & Equipment | B3: 12 | C3: 12 | D3: 12 | E3: 12 | F3: 12 | G3: 3 | H3: 9 | I3: 12 | J3: 12 | K3: 12 | L3: 12 | M3: 12
B4: 44561 | C4: 44926 | D4: 45291 | E4: 45657 | F4: 46022 | G4: 46112 | H4: 46387 | I4: 46752 | J4: 47118 | K4: 47483 | L4: 47848 | M4: 48213
A6: Opening Balance-WDV | C6: =B10 -> 24720.6 | D6: =C10 -> 23773.6 | E6: =D10 -> 24907.6 | F6: =E10 -> 25295 | G6: =F10 -> 28241 | H6: =G10 -> 28245 | I6: =H10 -> 29009.047 | J6: =I10 -> 30009.011 | ... M6: =L10 -> 33693.456
A7: Add: Net Addition during the Period | C7: =C8-C6 -> 877.4 | D7: =D8-D6 -> 3016.7 | E7: =E8-E6 -> 2334.4 | F7: =F8-F6 -> 5003 | G7: =G8-G6 -> 545.86558 | H7: ='McD IS'!H8*'Fixed Assets Schedule'!H14 -> 2375.7677 | I7: ='McD IS'!J8*'Fixed Assets Schedule'!$H$14 -> 3264.9484 | J7: ='McD IS'!K8*'Fixed Assets Schedule'!$H$14 -> 3460.8453 | K7: ='McD IS'!L8*'Fixed Assets Schedule'!$H$14 -> 3668.496 | L7: ='McD IS'!M8*'Fixed Assets Schedule'!$H$14 -> 3888.6058 | M7: ='McD IS'!N8*'Fixed Assets Schedule'!$H$14 -> 4121.9221
A8: Total Depreciable Assets During the Year | B8: =B10+B9 -> 26581 | C8: =C10+C9 -> 25598 | D8: =D10+D9 -> 26790.3 | E8: =E10+E9 -> 27242 | F8: =F10+F9 -> 30298 | G8: =G10+G9 -> 28786.866 | H8: =H6+H7 -> 30620.768 | I8: =I6+I7 -> 32273.995 | J8: =J6+J7 -> 33469.856 | K8: =K6+K7 -> 34789.443 | L8: =L6+L7 -> 36236.531 | M8: =M6+M7 -> 37815.378
A9: Less: Depreciation during the year | B9: ='McD IS'!B31 -> 1860.4 | C9: ='McD IS'!C31 -> 1824.4 | D9: ='McD IS'!D31 -> 1882.7 | E9: ='McD IS'!E31 -> 1947 | F9: ='McD IS'!F31 -> 2057 | G9: ='McD IS'!G31 -> 541.86558 | H9: =H8*H15*0.75 -> 1611.7207 | I9: =I8*$H$15 -> 2264.9842 | J9: =J8*$H$15 -> 2348.9096 | K9: =K8*$H$15 -> 2441.518 | L9: =L8*$H$15 -> 2543.0744 | M9: =M8*$H$15 -> 2653.8777
A10: Closing Balance-WDV | B10: ='McD-BS'!B14 -> 24720.6 | C10: ='McD-BS'!C14 -> 23773.6 | D10: ='McD-BS'!D14 -> 24907.6 | E10: ='McD-BS'!E14 -> 25295 | F10: ='McD-BS'!F14 -> 28241 | G10: ='McD-BS'!G14 -> 28245 | H10: =H8-H9 -> 29009.047 | I10: =I8-I9 -> 30009.011 | J10: =J8-J9 -> 31120.947 | K10: =K8-K9 -> 32347.925 | L10: =L8-L9 -> 33693.456 | M10: =M8-M9 -> 35161.501
A12: Capex as % of Opening PPE
A13: PPE Turnover Ratio = Net Oper rev (Norm.)/Total Depreciable Assets | B13: ='McD IS'!B8/'Fixed Assets Schedule'!B8 -> 0.8736654 | C13: ='McD IS'!C8/'Fixed Assets Schedule'!C8 -> 0.90564107 | D13: ='McD IS'!D8/'Fixed Assets Schedule'!D8 -> 0.95160189 | E13: ='McD IS'!E8/'Fixed Assets Schedule'!E8 -> 0.95147199 | F13: ='McD IS'!F8/'Fixed Assets Schedule'!F8 -> 0.8873523 | G13: ='McD IS'!G8/'Fixed Assets Schedule'!G8 -> 0.22638797 | H13: =AVERAGE(B13:F13) -> 0.91394653
A14: Capex as % of Sales | C14: =C7/'McD IS'!C8 -> 0.037847351 | D14: =D7/'McD IS'!D8 -> 0.1183312 | E14: =E7/'McD IS'!E8 -> 0.090061728 | F14: =F7/'McD IS'!F8 -> 0.1860889 | G14: =G7/'McD IS'!G8 -> 0.083760255 | H14: =AVERAGE(C14:F14) -> 0.10808229
A15: Depreciation Rate = Dep / TDA | B15: =B9/B8 -> 0.069989842 | C15: =C9/C8 -> 0.071271193 | D15: =D9/D8 -> 0.070275436 | E15: =E9/E8 -> 0.071470523 | F15: =F9/F8 -> 0.06789227 | G15: =G9/G8 -> 0.018823362 | H15: =AVERAGE(B15:F15) -> 0.070179853
A18: Depreciation (Operational)
A19: Depreciation (Corporate)
A20: Total Depreciation
A21: % Dep. Operational
A22: % Dep. Corporate
A24: written down value - asset value after reducing depreciation

Sheet Beta
C2: BETA CALCULATION
C4: Competitors | D4: Beta | E4: Market Cap | F4: R sq
C5: McDonald's | D5: =SLOPE($D$16:$D$171,$AB$16:$AB$171) -> 0.30143553 | F5: =RSQ($D$16:$D$171,$AB$16:$AB$171) -> 0.062572524
C6: Yum! Brands | D6: =SLOPE($H$17:$H$172,$AB$17:$AB$172) -> 0.34717764 | F6: =RSQ($H$16:$H$171,$AB$16:$AB$171) -> 0.06100843
C7: Restaurant Brands International | D7: =SLOPE($L$16:$L$171,$AB$16:$AB$171) -> 0.38570636 | F7: =RSQ($L$16:$L$171,$AB$16:$AB$171) -> 0.073377092
C8: Domino's Pizza | D8: =SLOPE($P$16:$P$171,$AB$16:$AB$171) -> 0.74374466 | F8: =RSQ($P$16:$P$171,$AB$16:$AB$171) -> 0.14458303
C9: Wendy's | D9: =SLOPE($T$16:T171,$AB$16:AB171) -> 0.41934942 | F9: =RSQ($T$16:V171,$AB$16:AD171) -> 0.04860569
C10: Chipotle (CMG) | D10: =SLOPE($X$16:X171,$AB$16:AB171) -> 0.93395764 | F10: =RSQ($X$16:Z171,$AB$16:AD171) -> 0.1674113
C12: Source : marketscreener.com, investing.com & yahoo finance
B14: McDonald's | F14: Yum! Brands | J14: Restaurant Brands International | N14: Domino's Pizza | R14: Wendy's | V14: Chipotle (CMG) | Z14: S&P 500
B15: Date | C15: Adj Close | D15: % Change | F15: Date | G15: Adj Close | H15: % Change | J15: Date | K15: Adj Close | L15: % Change | N15: Date | O15: Adj Close | P15: % Change | R15: Date | S15: Adj Close | T15: % Change | V15: Date | W15: Adj Close | X15: % Change | Z15: Date | AA15: Adj Close | AB15: % Change
B16: 06-28-2026 | C16: 267.11 | D16: =C16/C17-1 -> -0.0098235469 | F16: 46201 | G16: 158.24 | H16: =G16/G17-1 -> 0.011700019 | J16: 06-28-2026 | K16: 72.77 | L16: =K16/K17-1 -> -0.021119182 | N16: 06-28-2026 | O16: 289.39 | P16: =O16/O17-1 -> -0.029478838 | R16: 06-28-2026 | S16: 8.12 | T16: =S16/S17-1 -> 0.041025641 | V16: 06-28-2026 | W16: 32.85 | X16: =W16/W17-1 -> -0.014697061 | Z16: 06-28-2026 | AA16: 7440.43 | AB16: =AA16/AA17-1 -> 0.011750036
B17: 06-21-2026 | C17: 269.76 | D17: =C17/C18-1 -> -0.031764833 | F17: 46194 | G17: 156.41 | H17: =G17/G18-1 -> 0.029080861 | J17: 06-21-2026 | K17: 74.34 | L17: =K17/K18-1 -> 0.012254902 | N17: 06-21-2026 | O17: 298.18 | P17: =O17/O18-1 -> -0.04573239 | R17: 06-21-2026 | S17: 7.8 | T17: =S17/S18-1 -> 0.14705882 | V17: 06-21-2026 | W17: 33.34 | X17: =W17/W18-1 -> 0.026161896 | Z17: 46194 | AA17: 7354.02 | AB17: =AA17/AA18-1 -> -0.019539822
B18: 06-14-2026 | C18: 278.61 | D18: =C18/C19-1 -> -0.021768899 | F18: 46187 | G18: 151.99 | H18: =G18/G19-1 -> -0.01503467 | J18: 06-14-2026 | K18: 73.44 | L18: =K18/K19-1 -> -0.018837675 | N18: 06-14-2026 | O18: 312.47 | P18: =O18/O19-1 -> -0.035229097 | R18: 06-14-2026 | S18: 6.8 | T18: =S18/S19-1 -> 0.0014727541 | V18: 06-14-2026 | W18: 32.49 | X18: =W18/W19-1 -> 0.0080670183 | Z18: 46187 | AA18: 7500.58 | AB18: =AA18/AA19-1 -> 0.0093009987
B19: 46209 | C19: 284.81 | D19: =C19/C20-1 -> 0.017760149 | F19: 46180 | G19: 154.31 | H19: =G19/G20-1 -> 0.022801087 | J19: 46209 | K19: 74.85 | L19: =K19/K20-1 -> 0.03014038 | N19: 46209 | O19: 323.88 | P19: =O19/O20-1 -> 0.031497818 | R19: 46209 | S19: 6.79 | T19: =S19/S20-1 -> 0.011922504 | V19: 46209 | W19: 32.23 | X19: =W19/W20-1 -> 0.098500341 | Z19: 46180 | AA19: 7431.46 | AB19: =AA19/AA20-1 -> 0.0064628495
B20: 05-31-2026 | C20: 279.84 | D20: =C20/C21-1 -> 0.0022922636 | F20: 46173 | G20: 150.87 | H20: =G20/G21-1 -> 0.019736397 | J20: 05-31-2026 | K20: 72.66 | L20: =K20/K21-1 -> -0.027309237 | N20: 05-31-2026 | O20: 313.99 | P20: =O20/O21-1 -> 0.010979458 | R20: 05-31-2026 | S20: 6.71 | T20: =S20/S21-1 -> -0.12857143 | V20: 05-31-2026 | W20: 29.34 | X20: =W20/W21-1 -> -0.079096045 | Z20: 46173 | AA20: 7383.74 | AB20: =AA20/AA21-1 -> -0.025899531
B21: 05-24-2026 | C21: 279.2 | D21: =C21/C22-1 -> -0.010876112 | F21: 46166 | G21: 147.95 | H21: =G21/G22-1 -> -0.046406703 | J21: 05-24-2026 | K21: 74.7 | L21: =K21/K22-1 -> -0.0090209605 | N21: 05-24-2026 | O21: 310.58 | P21: =O21/O22-1 -> -0.018766587 | R21: 05-24-2026 | S21: 7.7 | T21: =S21/S22-1 -> -0.014084507 | V21: 05-24-2026 | W21: 31.86 | X21: =W21/W22-1 -> -0.03131651 | Z21: 46166 | AA21: 7580.06 | AB21: =AA21/AA22-1 -> 0.014262451
B22: 05-17-2026 | C22: 282.27 | D22: =C22/C23-1 -> 0.021274286 | F22: 46159 | G22: 155.15 | H22: =G22/G23-1 -> 0.034540241 | J22: 05-17-2026 | K22: 75.38 | L22: =K22/K23-1 -> -0.0060654008 | N22: 05-17-2026 | O22: 316.52 | P22: =O22/O23-1 -> 0.047074002 | R22: 05-17-2026 | S22: 7.81 | T22: =S22/S23-1 -> -0.026184539 | V22: 05-17-2026 | W22: 32.89 | X22: =W22/W23-1 -> 0.0073506891 | Z22: 46159 | AA22: 7473.47 | AB22: =AA22/AA23-1 -> 0.0087696565
B23: 46300 | C23: 276.39 | D23: =C23/C24-1 -> 0.0023209429 | F23: 46152 | G23: 149.97 | H23: =G23/G24-1 -> -0.013030602 | J23: 46300 | K23: 75.84 | L23: =K23/K24-1 -> -0.048550997 | N23: 46300 | O23: 302.29 | P23: =O23/O24-1 -> -0.065506368 | R23: 46300 | S23: 8.02 | T23: =S23/S24-1 -> 0.098630137 | V23: 46300 | W23: 32.65 | X23: =W23/W24-1 -> 0.0049245922 | Z23: 46152 | AA23: 7408.5 | AB23: =AA23/AA24-1 -> 0.0012934303
B24: 46086 | C24: 275.75 | D24: =C24/C25-1 -> -0.037991906 | F24: 46145 | G24: 151.95 | H24: =G24/G25-1 -> -0.040477393 | J24: 46086 | K24: 79.71 | L24: =K24/K25-1 -> -0.0039985006 | N24: 46086 | O24: 323.48 | P24: =O24/O25-1 -> -0.042306895 | R24: 46086 | S24: 7.3 | T24: =S24/S25-1 -> 0.089552239 | V24: 46086 | W24: 32.49 | X24: =W24/W25-1 -> -0.014857489 | Z24: 46145 | AA24: 7398.93 | AB24: =AA24/AA25-1 -> 0.02334816
B25: 04-26-2026 | C25: 286.64 | D25: =C25/C26-1 -> -0.042490647 | F25: 46138 | G25: 158.36 | H25: =G25/G26-1 -> -0.011979037 | J25: 04-26-2026 | K25: 80.03 | L25: =K25/K26-1 -> -0.010754017 | N25: 04-26-2026 | O25: 337.77 | P25: =O25/O26-1 -> -0.081722535 | R25: 04-26-2026 | S25: 6.7 | T25: =S25/S26-1 -> -0.06162465 | V25: 04-26-2026 | W25: 32.98 | X25: =W25/W26-1 -> -0.035954399 | Z25: 46138 | AA25: 7230.12 | AB25: =AA25/AA26-1 -> 0.0090773585
B26: 04-19-2026 | C26: 299.36 | D26: =C26/C27-1 -> -0.038540596 | F26: 46131 | G26: 160.28 | H26: =G26/G27-1 -> -0.015418638 | J26: 04-19-2026 | K26: 80.9 | L26: =K26/K27-1 -> 0.032941777 | N26: 04-19-2026 | O26: 367.83 | P26: =O26/O27-1 -> -0.011369134 | R26: 04-19-2026 | S26: 7.14 | T26: =S26/S27-1 -> 0.027338129 | V26: 04-19-2026 | W26: 34.21 | X26: =W26/W27-1 -> -0.045213508 | Z26: 46131 | AA26: 7165.08 | AB26: =AA26/AA27-1 -> 0.0054756766
B27: 46360 | C27: 311.36 | D27: =C27/C28-1 -> 0.018581523 | F27: 46124 | G27: 162.79 | H27: =G27/G28-1 -> 0.006367458 | J27: 46360 | K27: 78.32 | L27: =K27/K28-1 -> 0.025265087 | N27: 46360 | O27: 372.06 | P27: =O27/O28-1 -> 0.01669627 | R27: 46360 | S27: 6.95 | T27: =S27/S28-1 -> 0.0087082729 | V27: 46360 | W27: 35.83 | X27: =W27/W28-1 -> 0.051041361 | Z27: 46124 | AA27: 7126.06 | AB27: =AA27/AA28-1 -> 0.045353526
B28: 46146 | C28: 305.68 | D28: =C28/C29-1 -> -0.0047535326 | F28: 46117 | G28: 161.76 | H28: =G28/G29-1 -> 0.036325197 | J28: 46146 | K28: 76.39 | L28: =K28/K29-1 -> -0.0024810656 | N28: 46146 | O28: 365.95 | P28: =O28/O29-1 -> -0.013133056 | R28: 46146 | S28: 6.89 | T28: =S28/S29-1 -> 0.0014534884 | V28: 46146 | W28: 34.09 | X28: =W28/W29-1 -> 0.028045838 | Z28: 46117 | AA28: 6816.89 | AB28: =AA28/AA29-1 -> 0.03557816
B29: 03-29-2026 | C29: 307.14 | D29: =C29/C30-1 -> 0.0040536123 | F29: 46110 | G29: 156.09 | H29: =G29/G30-1 -> 0.013834762 | J29: 03-29-2026 | K29: 76.58 | L29: =K29/K30-1 -> 0.07224867 | N29: 03-29-2026 | O29: 370.82 | P29: =O29/O30-1 -> 0.065146206 | R29: 03-29-2026 | S29: 6.88 | T29: =S29/S30-1 -> 0.011764706 | V29: 03-29-2026 | W29: 33.16 | X29: =W29/W30-1 -> 0.074530136 | Z29: 46110 | AA29: 6582.69 | AB29: =AA29/AA30-1 -> 0.03357592
B30: 03-22-2026 | C30: 305.9 | D30: =C30/C31-1 -> -0.0095515622 | F30: 46103 | G30: 153.96 | H30: =G30/G31-1 -> -0.01566396 | J30: 03-22-2026 | K30: 71.42 | L30: =K30/K31-1 -> -0.03159322 | N30: 03-22-2026 | O30: 348.14 | P30: =O30/O31-1 -> -0.067523771 | R30: 03-22-2026 | S30: 6.8 | T30: =S30/S31-1 -> -0.04090268 | V30: 03-22-2026 | W30: 30.86 | X30: =W30/W31-1 -> -0.075217261 | Z30: 46103 | AA30: 6368.85 | AB30: =AA30/AA31-1 -> -0.021152758
B31: 03-15-2026 | C31: 308.85 | D31: =C31/C32-1 -> -0.05394229 | F31: 46096 | G31: 156.41 | H31: =G31/G32-1 -> -0.024875312 | J31: 03-15-2026 | K31: 73.75 | L31: =K31/K32-1 -> 0.015141087 | N31: 03-15-2026 | O31: 373.35 | P31: =O31/O32-1 -> -0.070413067 | R31: 03-15-2026 | S31: 7.09 | T31: =S31/S32-1 -> -0.011157601 | V31: 03-15-2026 | W31: 33.37 | X31: =W31/W32-1 -> 0.026137761 | Z31: 46096 | AA31: 6506.48 | AB31: =AA31/AA32-1 -> -0.018954523
B32: 46237 | C32: 326.46 | D32: =C32/C33-1 -> -0.0048771566 | F32: 46089 | G32: 160.4 | H32: =G32/G33-1 -> 0.0025 | J32: 46237 | K32: 72.65 | L32: =K32/K33-1 -> -0.017977832 | N32: 46237 | O32: 401.63 | P32: =O32/O33-1 -> -0.016600965 | R32: 46237 | S32: 7.17 | T32: =S32/S33-1 -> -0.033692722 | V32: 46237 | W32: 32.52 | X32: =W32/W33-1 -> -0.08057676 | Z32: 46089 | AA32: 6632.19 | AB32: =AA32/AA33-1 -> -0.015998469
B33: 46025 | C33: 328.06 | D33: =C33/C34-1 -> -0.03811646 | F33: 46082 | G33: 160 | H33: =G33/G34-1 -> -0.048525214 | J33: 46025 | K33: 73.98 | L33: =K33/K34-1 -> 0.031655278 | N33: 46025 | O33: 408.41 | P33: =O33/O34-1 -> 0.014658021 | R33: 46025 | S33: 7.42 | T33: =S33/S34-1 -> -0.031331593 | V33: 46025 | W33: 35.37 | X33: =W33/W34-1 -> -0.04970446 | Z33: 46082 | AA33: 6740.02 | AB33: =AA33/AA34-1 -> -0.020186426
B34: 02-22-2026 | C34: 341.06 | D34: =C34/C35-1 -> 0.035932327 | F34: 46075 | G34: 168.16 | H34: =G34/G35-1 -> 0.029572032 | J34: 02-22-2026 | K34: 71.71 | L34: =K34/K35-1 -> 0.041993607 | N34: 02-22-2026 | O34: 402.51 | P34: =O34/O35-1 -> 0.046540652 | R34: 02-22-2026 | S34: 7.66 | T34: =S34/S35-1 -> -0.05315204 | V34: 02-22-2026 | W34: 37.22 | X34: =W34/W35-1 -> -0.0085242408 | Z34: 46075 | AA34: 6878.88 | AB34: =AA34/AA35-1 -> -0.0044330206
B35: 02-15-2026 | C35: 329.23 | D35: =C35/C36-1 -> 0.0050369375 | F35: 46068 | G35: 163.33 | H35: =G35/G36-1 -> 0.017188765 | J35: 02-15-2026 | K35: 68.82 | L35: =K35/K36-1 -> 0.040520109 | N35: 02-15-2026 | O35: 384.61 | P35: =O35/O36-1 -> 0.024260985 | R35: 02-15-2026 | S35: 8.09 | T35: =S35/S36-1 -> 0.081550802 | V35: 02-15-2026 | W35: 37.54 | X35: =W35/W36-1 -> 0.03415978 | Z35: 46068 | AA35: 6909.51 | AB35: =AA35/AA36-1 -> 0.010728229
B36: 46236 | C36: 327.58 | D36: =C36/C37-1 -> 0.0012837755 | F36: 46061 | G36: 160.57 | H36: =G36/G37-1 -> -0.014484748 | J36: 46236 | K36: 66.14 | L36: =K36/K37-1 -> -0.067136812 | N36: 46236 | O36: 375.5 | P36: =O36/O37-1 -> -0.049078201 | R36: 46236 | S36: 7.48 | T36: =S36/S37-1 -> -0.067331671 | V36: 46236 | W36: 36.3 | X36: =W36/W37-1 -> -0.078446306 | Z36: 46061 | AA36: 6836.17 | AB36: =AA36/AA37-1 -> -0.013866971
B37: 46024 | C37: 327.16 | D37: =C37/C38-1 -> 0.038603175 | F37: 46054 | G37: 162.93 | H37: =G37/G38-1 -> 0.04778135 | J37: 46024 | K37: 70.9 | L37: =K37/K38-1 -> 0.05836692 | N37: 46024 | O37: 394.88 | P37: =O37/O38-1 -> -0.037652621 | R37: 46024 | S37: 8.02 | T37: =S37/S38-1 -> 0.029525032 | V37: 46024 | W37: 39.39 | X37: =W37/W38-1 -> 0.013377926 | Z37: 46054 | AA37: 6932.3 | AB37: =AA37/AA38-1 -> -0.00096987619
B38: 01-25-2026 | C38: 315 | D38: =C38/C39-1 -> 0.018593371 | F38: 46047 | G38: 155.5 | H38: =G38/G39-1 -> 0.016539191 | J38: 01-25-2026 | K38: 66.99 | L38: =K38/K39-1 -> -0.020614035 | N38: 01-25-2026 | O38: 410.33 | P38: =O38/O39-1 -> -0.0028432564 | R38: 01-25-2026 | S38: 7.79 | T38: =S38/S39-1 -> -0.074821853 | V38: 01-25-2026 | W38: 38.87 | X38: =W38/W39-1 -> -0.04893565 | Z38: 46047 | AA38: 6939.03 | AB38: =AA38/AA39-1 -> 0.0033865415
B39: 01-18-2026 | C39: 309.25 | D39: =C39/C40-1 -> 0.0059200468 | F39: 46040 | G39: 152.97 | H39: =G39/G40-1 -> -0.045488581 | J39: 01-18-2026 | K39: 68.4 | L39: =K39/K40-1 -> 0.0010244402 | N39: 01-18-2026 | O39: 411.5 | P39: =O39/O40-1 -> 0.028030379 | R39: 01-18-2026 | S39: 8.42 | T39: =S39/S40-1 -> 0.012019231 | V39: 01-18-2026 | W39: 40.87 | X39: =W39/W40-1 -> 0.022772773 | Z39: 46040 | AA39: 6915.61 | AB39: =AA39/AA40-1 -> -0.0035158451
B40: 46327 | C40: 307.43 | D40: =C40/C41-1 -> 0.0003579331 | F40: 46033 | G40: 160.26 | H40: =G40/G41-1 -> 0.030478395 | J40: 46327 | K40: 68.33 | L40: =K40/K41-1 -> -0.0097101449 | N40: 46327 | O40: 400.28 | P40: =O40/O41-1 -> -0.011873905 | R40: 46327 | S40: 8.32 | T40: =S40/S41-1 -> -0.038150289 | V40: 46327 | W40: 39.96 | X40: =W40/W41-1 -> -0.0037397158 | Z40: 46033 | AA40: 6940.01 | AB40: =AA40/AA41-1 -> -0.0037710227
B41: 46113 | C41: 307.32 | D41: =C41/C42-1 -> 0.013387852 | F41: 46026 | G41: 155.52 | H41: =G41/G42-1 -> 0.033424148 | J41: 46113 | K41: 69 | L41: =K41/K42-1 -> 0.017549034 | N41: 46113 | O41: 405.09 | P41: =O41/O42-1 -> -0.047474605 | R41: 46113 | S41: 8.65 | T41: =S41/S42-1 -> 0.05875153 | V41: 46113 | W41: 40.11 | X41: =W41/W42-1 -> 0.069885303 | Z41: 46026 | AA41: 6966.28 | AB41: =AA41/AA42-1 -> 0.015719249
B42: 12-28-2025 | C42: 303.26 | D42: =C42/C43-1 -> -0.023883095 | F42: 46019 | G42: 150.49 | H42: =G42/G43-1 -> -0.017945706 | J42: 12-28-2025 | K42: 67.81 | L42: =K42/K43-1 -> -0.02962221 | N42: 12-28-2025 | O42: 425.28 | P42: =O42/O43-1 -> -0.00065795657 | R42: 12-28-2025 | S42: 8.17 | T42: =S42/S43-1 -> -0.021556886 | V42: 12-28-2025 | W42: 37.49 | X42: =W42/W43-1 -> -0.0084633695 | Z42: 46019 | AA42: 6858.47 | AB42: =AA42/AA43-1 -> -0.010313221
B43: 12-21-2025 | C43: 310.68 | D43: =C43/C44-1 -> -0.016337386 | F43: 46012 | G43: 153.24 | H43: =G43/G44-1 -> -0.0033170732 | J43: 12-21-2025 | K43: 69.88 | L43: =K43/K44-1 -> -0.002426838 | N43: 12-21-2025 | O43: 425.56 | P43: =O43/O44-1 -> -0.013788788 | R43: 12-21-2025 | S43: 8.35 | T43: =S43/S44-1 -> -0.0035799523 | V43: 12-21-2025 | W43: 37.81 | X43: =W43/W44-1 -> 0.0045164718 | Z43: 46012 | AA43: 6929.94 | AB43: =AA43/AA44-1 -> 0.013964445
B44: 12-14-2025 | C44: 315.84 | D44: =C44/C45-1 -> -0.0027784794 | F44: 46005 | G44: 153.75 | H44: =G44/G45-1 -> 0.017807494 | J44: 12-14-2025 | K44: 70.05 | L44: =K44/K45-1 -> -0.011570481 | N44: 12-14-2025 | O44: 431.51 | P44: =O44/O45-1 -> -0.00050957775 | R44: 12-14-2025 | S44: 8.38 | T44: =S44/S45-1 -> -0.026713124 | V44: 12-14-2025 | W44: 37.64 | X44: =W44/W45-1 -> 0.041505257 | Z44: 46005 | AA44: 6834.5 | AB44: =AA44/AA45-1 -> 0.0010384611
B45: 45850 | C45: 316.72 | D45: =C45/C46-1 -> 0.017639688 | F45: 45998 | G45: 151.06 | H45: =G45/G46-1 -> 0.042080574 | J45: 45850 | K45: 70.87 | L45: =K45/K46-1 -> -0.036306772 | N45: 45850 | O45: 431.73 | P45: =O45/O46-1 -> 0.036442204 | R45: 45850 | S45: 8.61 | T45: =S45/S46-1 -> 0.02014218 | V45: 45850 | W45: 36.14 | X45: =W45/W46-1 -> 0.064820271 | Z45: 45998 | AA45: 6827.41 | AB45: =AA45/AA46-1 -> -0.0062572776
B46: 11-30-2025 | C46: 311.23 | D46: =C46/C47-1 -> -0.0018921172 | F46: 45991 | G46: 144.96 | H46: =G46/G47-1 -> -0.05384766 | J46: 11-30-2025 | K46: 73.54 | L46: =K46/K47-1 -> 0.015886172 | N46: 11-30-2025 | O46: 416.55 | P46: =O46/O47-1 -> -0.0073397993 | R46: 11-30-2025 | S46: 8.44 | T46: =S46/S47-1 -> -0.001183432 | V46: 11-30-2025 | W46: 33.94 | X46: =W46/W47-1 -> -0.016801854 | Z46: 45991 | AA46: 6870.4 | AB46: =AA46/AA47-1 -> 0.0031113622
B47: 11-23-2025 | C47: 311.82 | D47: =C47/C48-1 -> 0.0079844836 | F47: 45984 | G47: 153.21 | H47: =G47/G48-1 -> 0.0015034645 | J47: 11-23-2025 | K47: 72.39 | L47: =K47/K48-1 -> 0.026662885 | N47: 11-23-2025 | O47: 419.63 | P47: =O47/O48-1 -> 0.030019637 | R47: 11-23-2025 | S47: 8.45 | T47: =S47/S48-1 -> 0.019300362 | V47: 11-23-2025 | W47: 34.52 | X47: =W47/W48-1 -> 0.091368954 | Z47: 45984 | AA47: 6849.09 | AB47: =AA47/AA48-1 -> 0.037270994
B48: 11-16-2025 | C48: 309.35 | D48: =C48/C49-1 -> 0.0075562649 | F48: 45977 | G48: 152.98 | H48: =G48/G49-1 -> 0.026573614 | J48: 11-16-2025 | K48: 70.51 | L48: =K48/K49-1 -> 0.026645312 | N48: 11-16-2025 | O48: 407.4 | P48: =O48/O49-1 -> -0.0067290813 | R48: 11-16-2025 | S48: 8.29 | T48: =S48/S49-1 -> -0.038283063 | V48: 11-16-2025 | W48: 31.63 | X48: =W48/W49-1 -> 0.0019005385 | Z48: 45977 | AA48: 6602.99 | AB48: =AA48/AA49-1 -> -0.019471021
B49: 45911 | C49: 307.03 | D49: =C49/C50-1 -> 0.02459454 | F49: 45970 | G49: 149.02 | H49: =G49/G50-1 -> -0.00067060086 | J49: 45911 | K49: 68.68 | L49: =K49/K50-1 -> 0.013876587 | N49: 45911 | O49: 410.16 | P49: =O49/O50-1 -> -4.8759081e-05 | R49: 45911 | S49: 8.62 | T49: =S49/S50-1 -> -0.039018952 | V49: 45911 | W49: 31.57 | X49: =W49/W50-1 -> 0.032036613 | Z49: 45970 | AA49: 6734.11 | AB49: =AA49/AA50-1 -> 0.00078914517
B50: 45699 | C50: 299.66 | D50: =C50/C51-1 -> 0.0041215695 | F50: 45963 | G50: 149.12 | H50: =G50/G51-1 -> 0.078937848 | J50: 45699 | K50: 67.74 | L50: =K50/K51-1 -> 0.031207185 | N50: 45699 | O50: 410.18 | P50: =O50/O51-1 -> 0.029413241 | R50: 45699 | S50: 8.97 | T50: =S50/S51-1 -> 0.050351288 | V50: 45699 | W50: 30.59 | X50: =W50/W51-1 -> -0.034711265 | Z50: 45963 | AA50: 6728.8 | AB50: =AA50/AA51-1 -> -0.016286074
B51: 10-26-2025 | C51: 298.43 | D51: =C51/C52-1 -> -0.024068805 | F51: 45956 | G51: 138.21 | H51: =G51/G52-1 -> -0.035923549 | J51: 10-26-2025 | K51: 65.69 | L51: =K51/K52-1 -> -0.025660042 | N51: 10-26-2025 | O51: 398.46 | P51: =O51/O52-1 -> -0.039531408 | R51: 10-26-2025 | S51: 8.54 | T51: =S51/S52-1 -> -0.048997773 | V51: 10-26-2025 | W51: 31.69 | X51: =W51/W52-1 -> -0.2306385 | Z51: 45956 | AA51: 6840.2 | AB51: =AA51/AA52-1 -> 0.0071425521
B52: 10-19-2025 | C52: 305.79 | D52: =C52/C53-1 -> -0.007465351 | F52: 45949 | G52: 143.36 | H52: =G52/G53-1 -> -0.013012048 | J52: 10-19-2025 | K52: 67.42 | L52: =K52/K53-1 -> 0.00059364797 | N52: 10-19-2025 | O52: 414.86 | P52: =O52/O53-1 -> -0.0033632826 | R52: 10-19-2025 | S52: 8.98 | T52: =S52/S53-1 -> 0.011261261 | V52: 10-19-2025 | W52: 41.19 | X52: =W52/W53-1 -> -0.016005733 | Z52: 45949 | AA52: 6791.69 | AB52: =AA52/AA53-1 -> 0.019159635
B53: 46001 | C53: 308.09 | D53: =C53/C54-1 -> 0.037305141 | F53: 45942 | G53: 145.25 | H53: =G53/G54-1 -> 0.025631973 | J53: 46001 | K53: 67.38 | L53: =K53/K54-1 -> 0.0080789946 | N53: 46001 | O53: 416.26 | P53: =O53/O54-1 -> 0.024337426 | R53: 46001 | S53: 8.88 | T53: =S53/S54-1 -> 0.019517796 | V53: 46001 | W53: 41.86 | X53: =W53/W54-1 -> 0.051230537 | Z53: 45942 | AA53: 6664.01 | AB53: =AA53/AA54-1 -> 0.01701638
B54: 45787 | C54: 297.01 | D54: =C54/C55-1 -> -0.013190245 | F54: 45935 | G54: 141.62 | H54: =G54/G55-1 -> -0.060189794 | J54: 45787 | K54: 66.84 | L54: =K54/K55-1 -> -0.023948598 | N54: 45787 | O54: 406.37 | P54: =O54/O55-1 -> -0.047667034 | R54: 45787 | S54: 8.71 | T54: =S54/S55-1 -> -0.087958115 | V54: 45787 | W54: 39.82 | X54: =W54/W55-1 -> -0.046455939 | Z54: 45935 | AA54: 6552.51 | AB54: =AA54/AA55-1 -> -0.024312851
B55: 09-28-2025 | C55: 300.98 | D55: =C55/C56-1 -> -0.013956231 | F55: 45928 | G55: 150.69 | H55: =G55/G56-1 -> -0.013163065 | J55: 09-28-2025 | K55: 68.48 | L55: =K55/K56-1 -> 0.05499923 | N55: 09-28-2025 | O55: 426.71 | P55: =O55/O56-1 -> -0.020745841 | R55: 09-28-2025 | S55: 9.55 | T55: =S55/S56-1 -> 0.036916395 | V55: 09-28-2025 | W55: 41.76 | X55: =W55/W56-1 -> 0.041916168 | Z55: 45928 | AA55: 6715.79 | AB55: =AA55/AA56-1 -> 0.010850881
B56: 09-21-2025 | C56: 305.24 | D56: =C56/C57-1 -> 0.0094582975 | F56: 45921 | G56: 152.7 | H56: =G56/G57-1 -> 0.048331731 | J56: 09-21-2025 | K56: 64.91 | L56: =K56/K57-1 -> 0.018036386 | N56: 09-21-2025 | O56: 435.75 | P56: =O56/O57-1 -> 0.016421357 | R56: 09-21-2025 | S56: 9.21 | T56: =S56/S57-1 -> -0.012861736 | V56: 09-21-2025 | W56: 40.08 | X56: =W56/W57-1 -> 0.019328586 | Z56: 45921 | AA56: 6643.7 | AB56: =AA56/AA57-1 -> -0.0031000726
B57: 09-14-2025 | C57: 302.38 | D57: =C57/C58-1 -> -0.0098886706 | F57: 45914 | G57: 145.66 | H57: =G57/G58-1 -> -0.025620443 | J57: 09-14-2025 | K57: 63.76 | L57: =K57/K58-1 -> 0.013350286 | N57: 09-14-2025 | O57: 428.71 | P57: =O57/O58-1 -> -0.051631457 | R57: 09-14-2025 | S57: 9.33 | T57: =S57/S58-1 -> -0.034161491 | V57: 09-14-2025 | W57: 39.32 | X57: =W57/W58-1 -> 0.017861765 | Z57: 45914 | AA57: 6664.36 | AB57: =AA57/AA58-1 -> 0.012160764
B58: 45847 | C58: 305.4 | D58: =C58/C59-1 -> -0.028564158 | F58: 45907 | G58: 149.49 | H58: =G58/G59-1 -> 0.033960437 | J58: 45847 | K58: 62.92 | L58: =K58/K59-1 -> -0.0028526149 | N58: 45847 | O58: 452.05 | P58: =O58/O59-1 -> -0.025397236 | R58: 45847 | S58: 9.66 | T58: =S58/S59-1 -> -0.064859632 | V58: 45847 | W58: 38.63 | X58: =W58/W59-1 -> -0.059181685 | Z58: 45907 | AA58: 6584.29 | AB58: =AA58/AA59-1 -> 0.015858983
B59: 08-31-2025 | C59: 314.38 | D59: =C59/C60-1 -> 0.002679084 | F59: 45900 | G59: 144.58 | H59: =G59/G60-1 -> -0.016261822 | J59: 08-31-2025 | K59: 63.1 | L59: =K59/K60-1 -> -0.0036317701 | N59: 08-31-2025 | O59: 463.83 | P59: =O59/O60-1 -> 0.012066332 | R59: 08-31-2025 | S59: 10.33 | T59: =S59/S60-1 -> -0.026390198 | V59: 08-31-2025 | W59: 41.06 | X59: =W59/W60-1 -> -0.025628856 | Z59: 45900 | AA59: 6481.5 | AB59: =AA59/AA60-1 -> 0.0032877934
B60: 08-24-2025 | C60: 313.54 | D60: =C60/C61-1 -> -0.0016875219 | F60: 45893 | G60: 146.97 | H60: =G60/G61-1 -> -0.0060864273 | J60: 08-24-2025 | K60: 63.33 | L60: =K60/K61-1 -> -0.0011041009 | N60: 08-24-2025 | O60: 458.3 | P60: =O60/O61-1 -> 0.016208785 | R60: 08-24-2025 | S60: 10.61 | T60: =S60/S61-1 -> -0.0028195489 | V60: 08-24-2025 | W60: 42.14 | X60: =W60/W61-1 -> -0.034372136 | Z60: 45893 | AA60: 6460.26 | AB60: =AA60/AA61-1 -> -0.0010283118
B61: 08-17-2025 | C61: 314.07 | D61: =C61/C62-1 -> 0.016638073 | F61: 45886 | G61: 147.87 | H61: =G61/G62-1 -> -0.0020920502 | J61: 08-17-2025 | K61: 63.4 | L61: =K61/K62-1 -> -0.028947771 | N61: 08-17-2025 | O61: 450.99 | P61: =O61/O62-1 -> -0.00059832469 | R61: 08-17-2025 | S61: 10.64 | T61: =S61/S62-1 -> 0.0066225166 | V61: 08-17-2025 | W61: 43.64 | X61: =W61/W62-1 -> -0.0090826521 | Z61: 45886 | AA61: 6466.91 | AB61: =AA61/AA62-1 -> 0.0026527954
B62: 45938 | C62: 308.93 | D62: =C62/C63-1 -> 0.011393027 | F62: 45879 | G62: 148.18 | H62: =G62/G63-1 -> 0.048839185 | J62: 45938 | K62: 65.29 | L62: =K62/K63-1 -> 0.012248062 | N62: 45938 | O62: 451.26 | P62: =O62/O63-1 -> 0.025497682 | R62: 45938 | S62: 10.57 | T62: =S62/S63-1 -> 0.047571853 | V62: 45938 | W62: 44.04 | X62: =W62/W63-1 -> 0.062741313 | Z62: 45879 | AA62: 6449.8 | AB62: =AA62/AA63-1 -> 0.0094452574
B63: 45724 | C63: 305.45 | D63: =C63/C64-1 -> 0.0084519132 | F63: 45872 | G63: 141.28 | H63: =G63/G64-1 -> -0.028068244 | J63: 45724 | K63: 64.5 | L63: =K63/K64-1 -> -0.051749485 | N63: 45724 | O63: 440.04 | P63: =O63/O64-1 -> -0.056052513 | R63: 45724 | S63: 10.09 | T63: =S63/S64-1 -> 0.013052209 | V63: 45724 | W63: 41.44 | X63: =W63/W64-1 -> -0.025399812 | Z63: 45872 | AA63: 6389.45 | AB63: =AA63/AA64-1 -> 0.024276973
B64: 07-27-2025 | C64: 302.89 | D64: =C64/C65-1 -> 0.014808859 | F64: 45865 | G64: 145.36 | H64: =G64/G65-1 -> -0.0091342877 | J64: 07-27-2025 | K64: 68.02 | L64: =K64/K65-1 -> -0.02213916 | N64: 07-27-2025 | O64: 466.17 | P64: =O64/O65-1 -> -0.039873952 | R64: 07-27-2025 | S64: 9.96 | T64: =S64/S65-1 -> -0.074349442 | V64: 07-27-2025 | W64: 42.52 | X64: =W64/W65-1 -> -0.090675791 | Z64: 45865 | AA64: 6238.01 | AB64: =AA64/AA65-1 -> -0.023577788
B65: 07-20-2025 | C65: 298.47 | D65: =C65/C66-1 -> 0.004712694 | F65: 45858 | G65: 146.7 | H65: =G65/G66-1 -> -0.015171858 | J65: 07-20-2025 | K65: 69.56 | L65: =K65/K66-1 -> 0.0060746312 | N65: 07-20-2025 | O65: 485.53 | P65: =O65/O66-1 -> 0.042021676 | R65: 07-20-2025 | S65: 10.76 | T65: =S65/S66-1 -> 0.027698185 | V65: 07-20-2025 | W65: 46.76 | X65: =W65/W66-1 -> -0.13295012 | Z65: 45858 | AA65: 6388.64 | AB65: =AA65/AA66-1 -> 0.014586797
B66: 07-13-2025 | C66: 297.07 | D66: =C66/C67-1 -> -0.0094695075 | F66: 45851 | G66: 148.96 | H66: =G66/G67-1 -> -0.0055410909 | J66: 07-13-2025 | K66: 69.14 | L66: =K66/K67-1 -> 0.026730027 | N66: 07-13-2025 | O66: 465.95 | P66: =O66/O67-1 -> 0.0031648295 | R66: 07-13-2025 | S66: 10.47 | T66: =S66/S67-1 -> -0.049909256 | V66: 07-13-2025 | W66: 53.93 | X66: =W66/W67-1 -> -0.036964286 | Z66: 45851 | AA66: 6296.79 | AB66: =AA66/AA67-1 -> 0.0059171692
B67: 45815 | C67: 299.91 | D67: =C67/C68-1 -> 0.019824538 | F67: 45844 | G67: 149.79 | H67: =G67/G68-1 -> -0.0014 | J67: 45815 | K67: 67.34 | L67: =K67/K68-1 -> -0.022925131 | N67: 45815 | O67: 464.48 | P67: =O67/O68-1 -> 0.027201557 | R67: 45815 | S67: 11.02 | T67: =S67/S68-1 -> -0.056506849 | V67: 45815 | W67: 56 | X67: =W67/W68-1 -> -0.018748905 | Z67: 45844 | AA67: 6259.75 | AB67: =AA67/AA68-1 -> -0.0031213422
B68: 06-29-2025 | C68: 294.08 | D68: =C68/C69-1 -> 0.0086777568 | F68: 45837 | G68: 150 | H68: =G68/G69-1 -> 0.010713564 | J68: 06-29-2025 | K68: 68.92 | L68: =K68/K69-1 -> 0.054628921 | N68: 06-29-2025 | O68: 452.18 | P68: =O68/O69-1 -> 0.012970721 | R68: 06-29-2025 | S68: 11.68 | T68: =S68/S69-1 -> 0.010380623 | V68: 06-29-2025 | W68: 57.07 | X68: =W68/W69-1 -> 0.036693915 | Z68: 45837 | AA68: 6279.35 | AB68: =AA68/AA69-1 -> 0.017216717
B69: 06-22-2025 | C69: 291.55 | D69: =C69/C70-1 -> 0.014228067 | F69: 45830 | G69: 148.41 | H69: =G69/G70-1 -> 0.067237164 | J69: 06-22-2025 | K69: 65.35 | L69: =K69/K70-1 -> -0.010897533 | N69: 06-22-2025 | O69: 446.39 | P69: =O69/O70-1 -> -0.001989805 | R69: 06-22-2025 | S69: 11.56 | T69: =S69/S70-1 -> -0.037468776 | V69: 06-22-2025 | W69: 55.05 | X69: =W69/W70-1 -> 0.043008715 | Z69: 45830 | AA69: 6173.07 | AB69: =AA69/AA70-1 -> 0.034389327
B70: 06-15-2025 | C70: 287.46 | D70: =C70/C71-1 -> -0.047861946 | F70: 45823 | G70: 139.06 | H70: =G70/G71-1 -> -0.034305556 | J70: 06-15-2025 | K70: 66.07 | L70: =K70/K71-1 -> -0.017692536 | N70: 06-15-2025 | O70: 447.28 | P70: =O70/O71-1 -> -0.010770762 | R70: 06-15-2025 | S70: 12.01 | T70: =S70/S71-1 -> 0.074239714 | V70: 06-15-2025 | W70: 52.78 | X70: =W70/W71-1 -> 0.050557325 | Z70: 45823 | AA70: 5967.84 | AB70: =AA70/AA71-1 -> -0.0015275298
B71: 45875 | C71: 301.91 | D71: =C71/C72-1 -> -0.01773165 | F71: 45816 | G71: 144 | H71: =G71/G72-1 -> -0.0057308569 | J71: 45875 | K71: 67.26 | L71: =K71/K72-1 -> -0.056661992 | N71: 45875 | O71: 452.15 | P71: =O71/O72-1 -> -0.034300848 | R71: 45875 | S71: 11.18 | T71: =S71/S72-1 -> -0.043627032 | V71: 45875 | W71: 50.24 | X71: =W71/W72-1 -> -0.043047619 | Z71: 45816 | AA71: 5976.97 | AB71: =AA71/AA72-1 -> -0.0038980994
B72: 45663 | C72: 307.36 | D72: =C72/C73-1 -> -0.020678668 | F72: 45809 | G72: 144.83 | H72: =G72/G73-1 -> 0.0061831319 | J72: 45663 | K72: 71.3 | L72: =K72/K73-1 -> -0.0015404005 | N72: 45663 | O72: 468.21 | P72: =O72/O73-1 -> -0.011839939 | R72: 45663 | S72: 11.69 | T72: =S72/S73-1 -> 0.025438596 | V72: 45663 | W72: 52.5 | X72: =W72/W73-1 -> 0.048322684 | Z72: 45809 | AA72: 6000.36 | AB72: =AA72/AA73-1 -> 0.014999095
B73: 05-25-2025 | C73: 313.85 | D73: =C73/C74-1 -> -0.0022888387 | F73: 45802 | G73: 143.94 | H73: =G73/G74-1 -> -0.010381574 | J73: 05-25-2025 | K73: 71.41 | L73: =K73/K74-1 -> 0.019123733 | N73: 05-25-2025 | O73: 473.82 | P73: =O73/O74-1 -> -0.013758508 | R73: 05-25-2025 | S73: 11.4 | T73: =S73/S74-1 -> -0.0034965035 | V73: 05-25-2025 | W73: 50.08 | X73: =W73/W74-1 -> -0.010863125 | Z73: 45802 | AA73: 5911.69 | AB73: =AA73/AA74-1 -> 0.018761568
B74: 05-18-2025 | C74: 314.57 | D74: =C74/C75-1 -> -0.012680079 | F74: 45795 | G74: 145.45 | H74: =G74/G75-1 -> -0.017694334 | J74: 05-18-2025 | K74: 70.07 | L74: =K74/K75-1 -> -0.007788162 | N74: 05-18-2025 | O74: 480.43 | P74: =O74/O75-1 -> -0.02953237 | R74: 05-18-2025 | S74: 11.44 | T74: =S74/S75-1 -> -0.066884176 | V74: 05-18-2025 | W74: 50.63 | X74: =W74/W75-1 -> -0.032301223 | Z74: 45795 | AA74: 5802.82 | AB74: =AA74/AA75-1 -> -0.026107768
B75: 45966 | C75: 318.61 | D75: =C75/C76-1 -> 0.015716654 | F75: 45788 | G75: 148.07 | H75: =G75/G76-1 -> 0.0063889078 | J75: 45966 | K75: 70.62 | L75: =K75/K76-1 -> 0.051988679 | N75: 45966 | O75: 495.05 | P75: =O75/O76-1 -> 0.033723115 | R75: 45966 | S75: 12.26 | T75: =S75/S76-1 -> 0.021666667 | V75: 45966 | W75: 52.32 | X75: =W75/W76-1 -> 0.05229284 | Z75: 45788 | AA75: 5958.38 | AB75: =AA75/AA76-1 -> 0.052734054
B76: 45752 | C76: 313.68 | D76: =C76/C77-1 -> 0.0055135274 | F76: 45781 | G76: 147.13 | H76: =G76/G77-1 -> -0.01347727 | J76: 45752 | K76: 67.13 | L76: =K76/K77-1 -> 0.0076553588 | N76: 45752 | O76: 478.9 | P76: =O76/O77-1 -> -0.011782671 | R76: 45752 | S76: 12 | T76: =S76/S77-1 -> -0.043824701 | V76: 45752 | W76: 49.72 | X76: =W76/W77-1 -> -0.035686579 | Z76: 45781 | AA76: 5659.91 | AB76: =AA76/AA77-1 -> -0.0047057417
B77: 04-27-2025 | C77: 311.96 | D77: =C77/C78-1 -> -0.015091242 | F77: 45774 | G77: 149.14 | H77: =G77/G78-1 -> 0.012491514 | J77: 04-27-2025 | K77: 66.62 | L77: =K77/K78-1 -> 0.059141494 | N77: 04-27-2025 | O77: 484.61 | P77: =O77/O78-1 -> -0.0060913081 | R77: 04-27-2025 | S77: 12.55 | T77: =S77/S78-1 -> -0.01799687 | V77: 04-27-2025 | W77: 51.56 | X77: =W77/W78-1 -> -0.0042487447 | Z77: 45774 | AA77: 5686.67 | AB77: =AA77/AA78-1 -> 0.029222419
B78: 04-20-2025 | C78: 316.74 | D78: =C78/C79-1 -> 0.017475104 | F78: 45767 | G78: 147.3 | H78: =G78/G79-1 -> 0.027841742 | J78: 04-20-2025 | K78: 62.9 | L78: =K78/K79-1 -> -0.0050616893 | N78: 04-20-2025 | O78: 487.58 | P78: =O78/O79-1 -> 0.044650126 | R78: 04-20-2025 | S78: 12.78 | T78: =S78/S79-1 -> 0.0078864353 | V78: 04-20-2025 | W78: 51.78 | X78: =W78/W79-1 -> 0.074942911 | Z78: 45767 | AA78: 5525.21 | AB78: =AA78/AA79-1 -> 0.045906449
B79: 04-13-2025 | C79: 311.3 | D79: =C79/C80-1 -> 0.0045175863 | F79: 45760 | G79: 143.31 | H79: =G79/G80-1 -> -0.011655172 | J79: 04-13-2025 | K79: 63.22 | L79: =K79/K80-1 -> 0.0052472571 | N79: 04-13-2025 | O79: 466.74 | P79: =O79/O80-1 -> 0.0098881364 | R79: 04-13-2025 | S79: 12.68 | T79: =S79/S80-1 -> -0.0086004691 | V79: 04-13-2025 | W79: 48.17 | X79: =W79/W80-1 -> -0.031953376 | Z79: 45760 | AA79: 5282.7 | AB79: =AA79/AA80-1 -> -0.01503908
B80: 45812 | C80: 309.9 | D80: =C80/C81-1 -> 0.032621372 | F80: 45753 | G80: 145 | H80: =G80/G81-1 -> -0.019143611 | J80: 45812 | K80: 62.89 | L80: =K80/K81-1 -> -0.010852469 | N80: 45812 | O80: 462.17 | P80: =O80/O81-1 -> 0.040431328 | R80: 45812 | S80: 12.79 | T80: =S80/S81-1 -> -0.038345865 | V80: 45812 | W80: 49.76 | X80: =W80/W81-1 -> 0.052230916 | Z80: 45753 | AA80: 5363.36 | AB80: =AA80/AA81-1 -> 0.05701132
B81: 03-30-2025 | C81: 300.11 | D81: =C81/C82-1 -> -0.022729493 | F81: 45746 | G81: 147.83 | H81: =G81/G82-1 -> -0.050911659 | J81: 03-30-2025 | K81: 63.58 | L81: =K81/K82-1 -> -0.014569126 | N81: 03-30-2025 | O81: 444.21 | P81: =O81/O82-1 -> -0.0065083199 | R81: 03-30-2025 | S81: 13.3 | T81: =S81/S82-1 -> -0.090909091 | V81: 03-30-2025 | W81: 47.29 | X81: =W81/W82-1 -> -0.05249449 | Z81: 45746 | AA81: 5074.08 | AB81: =AA81/AA82-1 -> -0.090819826
B82: 03-23-2025 | C82: 307.09 | D82: =C82/C83-1 -> 0.005402043 | F82: 45739 | G82: 155.76 | H82: =G82/G83-1 -> -0.0063157895 | J82: 03-23-2025 | K82: 64.52 | L82: =K82/K83-1 -> -0.037014925 | N82: 03-23-2025 | O82: 447.12 | P82: =O82/O83-1 -> -0.030949285 | R82: 03-23-2025 | S82: 14.63 | T82: =S82/S83-1 -> -0.041284404 | V82: 03-23-2025 | W82: 49.91 | X82: =W82/W83-1 -> 0.028436019 | Z82: 45739 | AA82: 5580.94 | AB82: =AA82/AA83-1 -> -0.015283473
B83: 03-16-2025 | C83: 305.44 | D83: =C83/C84-1 -> 0.018710603 | F83: 45732 | G83: 156.75 | H83: =G83/G84-1 -> 0.010964205 | J83: 03-16-2025 | K83: 67 | L83: =K83/K84-1 -> 0.014229488 | N83: 03-16-2025 | O83: 461.4 | P83: =O83/O84-1 -> 0.084167489 | R83: 03-16-2025 | S83: 15.26 | T83: =S83/S84-1 -> -0.0058631922 | V83: 03-16-2025 | W83: 48.53 | X83: =W83/W84-1 -> -0.029982011 | Z83: 45732 | AA83: 5667.56 | AB83: =AA83/AA84-1 -> 0.005075422
B84: 45903 | C84: 299.83 | D84: =C84/C85-1 -> -0.06679324 | F84: 45725 | G84: 155.05 | H84: =G84/G85-1 -> -0.046022273 | J84: 45903 | K84: 66.06 | L84: =K84/K85-1 -> -0.050452781 | N84: 45903 | O84: 425.58 | P84: =O84/O85-1 -> -0.098442962 | R84: 45903 | S84: 15.35 | T84: =S84/S85-1 -> -0.01159047 | V84: 45903 | W84: 50.03 | X84: =W84/W85-1 -> -0.0039816843 | Z84: 45725 | AA84: 5638.94 | AB84: =AA84/AA85-1 -> -0.022747912
B85: 45691 | C85: 321.29 | D85: =C85/C86-1 -> 0.042032887 | F85: 45718 | G85: 162.53 | H85: =G85/G86-1 -> 0.039393746 | J85: 45691 | K85: 69.57 | L85: =K85/K86-1 -> 0.066206897 | N85: 45691 | O85: 472.05 | P85: =O85/O86-1 -> -0.036062159 | R85: 45691 | S85: 15.53 | T85: =S85/S86-1 -> 0.0019354839 | V85: 45691 | W85: 50.23 | X85: =W85/W86-1 -> -0.069297758 | Z85: 45718 | AA85: 5770.2 | AB85: =AA85/AA86-1 -> -0.030951381
B86: 02-23-2025 | C86: 308.33 | D86: =C86/C87-1 -> 0.011548178 | F86: 45711 | G86: 156.37 | H86: =G86/G87-1 -> 0.051226891 | J86: 02-23-2025 | K86: 65.25 | L86: =K86/K87-1 -> 0.047183438 | N86: 02-23-2025 | O86: 489.71 | P86: =O86/O87-1 -> 0.059130134 | R86: 02-23-2025 | S86: 15.5 | T86: =S86/S87-1 -> 0.019066404 | V86: 02-23-2025 | W86: 53.97 | X86: =W86/W87-1 -> 0.047757717 | Z86: 45711 | AA86: 5954.5 | AB86: =AA86/AA87-1 -> -0.0097503297
B87: 02-16-2025 | C87: 304.81 | D87: =C87/C88-1 -> -0.012121212 | F87: 45704 | G87: 148.75 | H87: =G87/G88-1 -> 0.0056791292 | J87: 02-16-2025 | K87: 62.31 | L87: =K87/K88-1 -> -0.034252945 | N87: 02-16-2025 | O87: 462.37 | P87: =O87/O88-1 -> -0.02997944 | R87: 02-16-2025 | S87: 15.21 | T87: =S87/S88-1 -> 0.063636364 | V87: 02-16-2025 | W87: 51.51 | X87: =W87/W88-1 -> -0.097582341 | Z87: 45704 | AA87: 6013.13 | AB87: =AA87/AA88-1 -> -0.016599533
B88: 45902 | C88: 308.55 | D88: =C88/C89-1 -> 0.04841998 | F88: 45697 | G88: 147.91 | H88: =G88/G89-1 -> 0.030300919 | J88: 45902 | K88: 64.52 | L88: =K88/K89-1 -> 0.0059245401 | N88: 45902 | O88: 476.66 | P88: =O88/O89-1 -> 0.021253803 | R88: 45902 | S88: 14.3 | T88: =S88/S89-1 -> -0.009009009 | V88: 45902 | W88: 57.08 | X88: =W88/W89-1 -> -0.0033176183 | Z88: 45697 | AA88: 6114.63 | AB88: =AA88/AA89-1 -> 0.014709616
B89: 45690 | C89: 294.3 | D89: =C89/C90-1 -> 0.019397298 | F89: 45690 | G89: 143.56 | H89: =G89/G90-1 -> 0.10007663 | J89: 45690 | K89: 64.14 | L89: =K89/K90-1 -> 0.042248944 | N89: 45690 | O89: 466.74 | P89: =O89/O90-1 -> 0.039232276 | R89: 45690 | S89: 14.43 | T89: =S89/S90-1 -> -0.026972353 | V89: 45690 | W89: 57.27 | X89: =W89/W90-1 -> -0.018508997 | Z89: 45690 | AA89: 6025.99 | AB89: =AA89/AA90-1 -> -0.0024070736
B90: 01-26-2025 | C90: 288.7 | D90: =C90/C91-1 -> 0.011350102 | F90: 45683 | G90: 130.5 | H90: =G90/G91-1 -> 0.017464525 | J90: 01-26-2025 | K90: 61.54 | L90: =K90/K91-1 -> -0.0086984536 | N90: 01-26-2025 | O90: 449.12 | P90: =O90/O91-1 -> 0.034290583 | R90: 01-26-2025 | S90: 14.83 | T90: =S90/S91-1 -> 0.037062937 | V90: 01-26-2025 | W90: 58.35 | X90: =W90/W91-1 -> 0.029100529 | Z90: 45683 | AA90: 6040.53 | AB90: =AA90/AA91-1 -> -0.0099504363
B91: 01-19-2025 | C91: 285.46 | D91: =C91/C92-1 -> 0.016052678 | F91: 45676 | G91: 128.26 | H91: =G91/G92-1 -> 0.023459943 | J91: 01-19-2025 | K91: 62.08 | L91: =K91/K92-1 -> 0.026455026 | N91: 01-19-2025 | O91: 434.23 | P91: =O91/O92-1 -> 0.016099216 | R91: 01-19-2025 | S91: 14.3 | T91: =S91/S92-1 -> -0.020547945 | V91: 01-19-2025 | W91: 56.7 | X91: =W91/W92-1 -> -0.014255911 | Z91: 45676 | AA91: 6101.24 | AB91: =AA91/AA92-1 -> 0.017439708
B92: 45992 | C92: 280.95 | D92: =C92/C93-1 -> -0.0048173993 | F92: 45669 | G92: 125.32 | H92: =G92/G93-1 -> 0.016795132 | J92: 45992 | K92: 60.48 | L92: =K92/K93-1 -> -0.0065703022 | N92: 45992 | O92: 427.35 | P92: =O92/O93-1 -> 0.062187756 | R92: 45992 | S92: 14.6 | T92: =S92/S93-1 -> -0.022757697 | V92: 45992 | W92: 57.52 | X92: =W92/W93-1 -> 0.018053097 | Z92: 45669 | AA92: 5996.66 | AB92: =AA92/AA93-1 -> 0.029109119
B93: 45778 | C93: 282.31 | D93: =C93/C94-1 -> -0.042302734 | F93: 45662 | G93: 123.25 | H93: =G93/G94-1 -> -0.076363909 | J93: 45778 | K93: 60.88 | L93: =K93/K94-1 -> -0.062519249 | N93: 45778 | O93: 402.33 | P93: =O93/O94-1 -> -0.081606099 | R93: 45778 | S93: 14.94 | T93: =S93/S94-1 -> -0.07606679 | V93: 45778 | W93: 56.5 | X93: =W93/W94-1 -> -0.05360134 | Z93: 45662 | AA93: 5827.04 | AB93: =AA93/AA94-1 -> -0.019424583
B94: 12-29-2024 | C94: 294.78 | D94: =C94/C95-1 -> 0.0039506846 | F94: 45655 | G94: 133.44 | H94: =G94/G95-1 -> -0.013236708 | J94: 12-29-2024 | K94: 64.94 | L94: =K94/K95-1 -> -0.0091547147 | N94: 12-29-2024 | O94: 438.08 | P94: =O94/O95-1 -> 0.019691821 | R94: 12-29-2024 | S94: 16.17 | T94: =S94/S95-1 -> -0.02 | V94: 12-29-2024 | W94: 59.7 | X94: =W94/W95-1 -> -0.017769003 | Z94: 45655 | AA94: 5942.47 | AB94: =AA94/AA95-1 -> -0.0047514253
B95: 12-22-2024 | C95: 293.62 | D95: =C95/C96-1 -> 0.0032116988 | F95: 45648 | G95: 135.23 | H95: =G95/G96-1 -> 0.021683288 | J95: 12-22-2024 | K95: 65.54 | L95: =K95/K96-1 -> -0.018421447 | N95: 12-22-2024 | O95: 429.62 | P95: =O95/O96-1 -> 0.0080717068 | R95: 12-22-2024 | S95: 16.5 | T95: =S95/S96-1 -> -0.009009009 | V95: 12-22-2024 | W95: 60.78 | X95: =W95/W96-1 -> -0.017617585 | Z95: 45648 | AA95: 5970.84 | AB95: =AA95/AA96-1 -> 0.0067427097
B96: 12-15-2024 | C96: 292.68 | D96: =C96/C97-1 -> -0.013216453 | F96: 45641 | G96: 132.36 | H96: =G96/G97-1 -> -0.033868613 | J96: 12-15-2024 | K96: 66.77 | L96: =K96/K97-1 -> -0.022114821 | N96: 12-15-2024 | O96: 426.18 | P96: =O96/O97-1 -> -0.059558223 | R96: 12-15-2024 | S96: 16.65 | T96: =S96/S97-1 -> -0.026884863 | V96: 12-15-2024 | W96: 61.87 | X96: =W96/W97-1 -> -0.042111782 | Z96: 45641 | AA96: 5930.85 | AB96: =AA96/AA97-1 -> -0.0198708
B97: 45516 | C97: 296.6 | D97: =C97/C98-1 -> -0.0079603987 | F97: 45634 | G97: 137 | H97: =G97/G98-1 -> -0.0045774904 | J97: 45516 | K97: 68.28 | L97: =K97/K98-1 -> -0.010291347 | N97: 45516 | O97: 453.17 | P97: =O97/O98-1 -> -0.013968972 | R97: 45516 | S97: 17.11 | T97: =S97/S98-1 -> -0.021167048 | V97: 45516 | W97: 64.59 | X97: =W97/W98-1 -> -0.012385321 | Z97: 45634 | AA97: 6051.09 | AB97: =AA97/AA98-1 -> -0.0064332123
B98: 45303 | C98: 298.98 | D98: =C98/C99-1 -> 0.010033445 | F98: 45627 | G98: 137.63 | H98: =G98/G99-1 -> -0.0094285303 | J98: 45303 | K98: 68.99 | L98: =K98/K99-1 -> -0.0089067663 | N98: 45303 | O98: 459.59 | P98: =O98/O99-1 -> -0.034860035 | R98: 45303 | S98: 17.48 | T98: =S98/S99-1 -> -0.047930283 | V98: 45303 | W98: 65.4 | X98: =W98/W99-1 -> 0.063068921 | Z98: 45627 | AA98: 6090.27 | AB98: =AA98/AA99-1 -> 0.009596544
B99: 11-24-2024 | C99: 296.01 | D99: =C99/C100-1 -> 0.019739562 | F99: 45620 | G99: 138.94 | H99: =G99/G100-1 -> 0.027130923 | J99: 11-24-2024 | K99: 69.61 | L99: =K99/K100-1 -> 0.0073806078 | N99: 11-24-2024 | O99: 476.19 | P99: =O99/O100-1 -> 0.050380501 | R99: 11-24-2024 | S99: 18.36 | T99: =S99/S100-1 -> 0.021134594 | V99: 11-24-2024 | W99: 61.52 | X99: =W99/W100-1 -> -0.0079019513 | Z99: 45620 | AA99: 6032.38 | AB99: =AA99/AA100-1 -> 0.010560631
B100: 11-17-2024 | C100: 290.28 | D100: =C100/C101-1 -> -0.0080306189 | F100: 45613 | G100: 135.27 | H100: =G100/G101-1 -> 0.012575792 | J100: 11-17-2024 | K100: 69.1 | L100: =K100/K101-1 -> 0.023400474 | N100: 11-17-2024 | O100: 453.35 | P100: =O100/O101-1 -> 0.053249077 | R100: 11-17-2024 | S100: 17.98 | T100: =S100/S101-1 -> -0.0077262693 | V100: 11-17-2024 | W100: 62.01 | X100: =W100/W101-1 -> 0.057649667 | Z100: 45613 | AA100: 5969.34 | AB100: =AA100/AA101-1 -> 0.016815941
B101: 45576 | C101: 292.63 | D101: =C101/C102-1 -> -0.021206141 | F101: 45606 | G101: 133.59 | H101: =G101/G102-1 -> -0.026382917 | J101: 45576 | K101: 67.52 | L101: =K101/K102-1 -> -0.0069127813 | N101: 45576 | O101: 430.43 | P101: =O101/O102-1 -> -0.063733061 | R101: 45576 | S101: 18.12 | T101: =S101/S102-1 -> -0.072671443 | V101: 45576 | W101: 58.63 | X101: =W101/W102-1 -> -0.003060704 | Z101: 45606 | AA101: 5870.62 | AB101: =AA101/AA102-1 -> -0.020835488
B102: 45362 | C102: 298.97 | D102: =C102/C103-1 -> 0.012736696 | F102: 45599 | G102: 137.21 | H102: =G102/G103-1 -> 0.036799154 | J102: 45362 | K102: 67.99 | L102: =K102/K103-1 -> -0.028436696 | N102: 45362 | O102: 459.73 | P102: =O102/O103-1 -> 0.079609234 | R102: 45362 | S102: 19.54 | T102: =S102/S103-1 -> -0.006103764 | V102: 45362 | W102: 58.81 | X102: =W102/W103-1 -> 0.003754907 | Z102: 45599 | AA102: 5995.54 | AB102: =AA102/AA103-1 -> 0.046561234
B103: 10-27-2024 | C103: 295.21 | D103: =C103/C104-1 -> 0.0088855473 | F103: 45592 | G103: 132.34 | H103: =G103/G104-1 -> -0.0052615755 | J103: 10-27-2024 | K103: 69.98 | L103: =K103/K104-1 -> -0.0079387582 | N103: 10-27-2024 | O103: 425.83 | P103: =O103/O104-1 -> 0.029047147 | R103: 10-27-2024 | S103: 19.66 | T103: =S103/S104-1 -> 0.0061412487 | V103: 10-27-2024 | W103: 58.59 | X103: =W103/W104-1 -> -0.014300135 | Z103: 45592 | AA103: 5728.8 | AB103: =AA103/AA104-1 -> -0.013656743
B104: 10-20-2024 | C104: 292.61 | D104: =C104/C105-1 -> -0.075657063 | F104: 45585 | G104: 133.04 | H104: =G104/G105-1 -> -0.0091606465 | J104: 10-20-2024 | K104: 70.54 | L104: =K104/K105-1 -> -0.00014174344 | N104: 10-20-2024 | O104: 413.81 | P104: =O104/O105-1 -> -0.035070537 | R104: 10-20-2024 | S104: 19.54 | T104: =S104/S105-1 -> -0.0081218274 | V104: 10-20-2024 | W104: 59.44 | X104: =W104/W105-1 -> 0.00084189257 | Z104: 45585 | AA104: 5808.12 | AB104: =AA104/AA105-1 -> -0.0096424863
...

Sheet WACC
B1: McDONALD’S CORPORATION WACC Calculation
B2: (in USD million except per Share Data)
B4: Cost of Equity | F4: Cost of Debt | K4: Weighted Average Cost of Capital (WACC)
B6: CHOOSE Beta Type | C6: 1 | D6: =IF(C6=A30,B30,B31) -> Bottoms Up Beta | F6: CHOOSE Cost of Debt | G6: 2 | K6: Particulars | L6: Weight | M6: Particulars | N6: Cost | O6: Value
B7: 1 for Bottom-up & 2 for Regression Beta | E7: 1 | F7: =K33 -> Cost of debt (using historical wgted avg interest rate) | K7: Debt (%) | L7: =E27 -> 0.022410703 | M7: Cost of debt (%) | N7: =I12 -> 0.0432288 | O7: =N7*L7 -> 0.0009687878
E8: 2 | F8: =K40 -> Cost of debt (using Credit Rating Method) | K8: Equity (%) | L8: =G27 -> 0.9775893 | M8: Cost of equity (%) | N8: =D14 -> 0.065066452 | O8: =N8*L8 -> 0.063608267
B9: Cost of Equity calculation using Capital Asset Pricing Model (CAPM) | E9: 3 | F9: =K50 -> Cost of debt (using Synthetic Rating Method) | K9: WACC | N9: WACC | O9: =O7+O8 -> 0.064577055
B10: Particulars | C10: Notes | D10: Value
B11: Risk-free rate (%) | C11: 10 year Treasury rate | D11: 0.04362 | F11: ACTIVE CHOICE
B12: Beta | C12: =D6 -> Bottoms Up Beta | D12: =CHOOSE(C6,C30,C31) -> 0.42637082 | F12: =IF(G6=E7, F7, IF(G6=E8, F8, F9)) -> Cost of debt (using Credit Rating Method) | I12: =CHOOSE(G6,M37,M47,M56) -> 0.0432288
B13: Equity market risk premium (%) | D13: 0.0503
B14: Cost of Equity Capital (%) | D14: =D11+(D12*D13) -> 0.065066452
B16: Calculation of Bottom-Up Beta
B17: Particulars | C17: Levered beta or Regression Beta or EQUITY Beta | D17: Average Debt | E17: Avg Debt/(Avg Debt + Avg Equity) | F17: Average Equity (Mkt. Cap) | G17: Avg Equity/(Avg Debt + Avg Equity) | H17: Average Debt / Average Equity | I17: Unlevered beta or ASSET Beta (represents Business Risk) | J17: Relevered beta
B18: Yum! Brands | C18: =Beta!D6 -> 0.34717764 | D18: =AVERAGE(C41:C43) -> 12872.333 | E18: =D18/(D18+F18) -> 0.23766619 | F18: =AVERAGE(F41:F43) -> 41289.067 | G18: =F18/(D18+F18) -> 0.76233381 | H18: =D18/F18 -> 0.31176131 | I18: =C18/(1+(1-$I$27)*H18) -> 0.27856858
B19: Restaurant Brands International | C19: =Beta!D7 -> 0.38570636 | D19: =AVERAGE(C46:C48) -> 15762.667 | E19: =D19/(D19+F19) -> 0.33089322 | F19: =AVERAGE(F46:F48) -> 31874.05 | G19: =F19/(D19+F19) -> 0.66910678 | H19: =D19/F19 -> 0.49452977 | I19: =C19/(1+(1-$I$27)*H19) -> 0.2773512
B20: Domino's Pizza | C20: =Beta!D8 -> 0.74374466 | D20: =AVERAGE(C51:C53) -> 5127.0967 | E20: =D20/(D20+F20) -> 0.26963247 | F20: =AVERAGE(F51:F53) -> 13888.034 | G20: =F20/(D20+F20) -> 0.73036753 | H20: =D20/F20 -> 0.36917369 | I20: =C20/(1+(1-$I$27)*H20) -> 0.57581099
B21: Chipotle (CMG) | C21: =Beta!D10 -> 0.93395764 | D21: =AVERAGE(C56:C58) -> 4954.1033 | E21: =D21/(D21+F21) -> 0.07799795 | F21: =AVERAGE(F56:F58) -> 58561.711 | G21: =F21/(D21+F21) -> 0.92200205 | H21: =D21/F21 -> 0.084596287 | I21: =C21/(1+(1-$I$27)*H21) -> 0.87545036
B22: Wendy's | C22: =Beta!D9 -> 0.41934942 | D22: =AVERAGE(C61:C63) -> 4118.06 | E22: =D22/(D22+F22) -> 0.66500728 | F22: =AVERAGE(F61:F63) -> 2074.4436 | G22: =F22/(D22+F22) -> 0.33499272 | H22: =D22/F22 -> 1.9851395 | I22: =C22/(1+(1-$I$27)*H22) -> 0.16328151
H24: Industry Average | I24: =AVERAGE(I18:I22) -> 0.43409253 | J24: =I24/(1+(1-I27)*H27) -> 0.42637082
B26: Target Company | C26: Levered beta | D26: Average Debt | E26: Avg Debt/(Avg Debt + Avg Equity) | F26: Average Equity (Mkt. Cap) | G26: Avg Equity/(Avg Debt + Avg Equity) | H26: Average Debt / Average Equity | I26: Tax Rate
B27: McDonald's | C27: =Beta!D5 -> 0.30143553 | D27: =AVERAGE(C36:C38) -> 4954.1033 | E27: =D27/(D27+F27) -> 0.022410703 | F27: =AVERAGE(F36:F38) -> 216105.6 | G27: =F27/(D27+F27) -> 0.9775893 | H27: =D27/F27 -> 0.022924456 | I27: 0.21
B29: Beta Calculation for Target Company - McDONALD’S CORPORATION
A30: 1 | B30: Bottoms Up Beta | C30: =J24 -> 0.42637082
A31: 2 | B31: Regression Beta | C31: =C27 -> 0.30143553 | K31: Cost of Debt Calculation
B33: Calculation of Capital Structure of Target & Peer Group Companies | K33: Cost of debt (using historical wgted avg interest rate)
C34: Total Debt (in $ million) | D34: Equity | K34: Particulars | L34: Notes | M34: Value
A35: TARGET | B35: McDONALD’S CORPORATION | D35: Share Price (in $) | E35: Shares O/S | F35: M.Cap | G35: Tax Rate | K35: Debt Borrowing Rate (%) | M35: ='Debt Schedule'!H15 -> 0.038329755
B36: 46103 | C36: 5245.88 | D36: =Beta!C30 -> 305.9 | E36: 713.5 | F36: =D36*E36 -> 218259.65 | G36: 0.21 | K36: Income Tax Rate (%) | M36: =G36 -> 0.21
B37: 46019 | C37: 5075.81 | D37: =Beta!C42 -> 303.26 | E37: 716.4 | F37: =D37*E37 -> 217255.46 | G37: 0.21 | K37: After-tax Cost of Debt (%) | M37: =M35*(1-M36) -> 0.030280506
B38: 45655 | C38: 4540.62 | D38: =Beta!C94 -> 294.78 | E38: 721.9 | F38: =D38*E38 -> 212801.68 | G38: 0.21
A40: PEER 1 | B40: Yum! Brands | K40: Cost of debt (using Credit Rating Method)
B41: 46112 | C41: 13144 | D41: =Beta!G29 -> 156.09 | E41: 279 | F41: =D41*E41 -> 43549.11 | G41: 0.21 | H41: Diluted Weighted Average Shares Outstanding | K41: Particulars | L41: Notes | M41: Value
B42: 46022 | C42: 13187 | D42: =Beta!G42 -> 150.49 | E42: 281 | F42: =D42*E42 -> 42287.69 | G42: 0.21 | K42: Riskfree Rate | M42: =D11 -> 0.04362
B43: 45657 | C43: 12286 | D43: =Beta!G94 -> 133.44 | E43: 285 | F43: =D43*E43 -> 38030.4 | G43: 0.21 | K43: Credit Rating | L43: S&P | M43: BBB
K44: Credit Spread | L44: Prof. Damodaran | M44: 0.0111
A45: PEER 2 | B45: Restaurant Brands International | K45: Debt Borrowing Rate (%) | M45: =M42+M44 -> 0.05472
B46: 46112 | C46: 15683 | D46: =Beta!K29 -> 76.58 | E46: 459 | F46: =D46*E46 -> 35150.22 | G46: 0.21 | K46: Income Tax Rate (%) | M46: =G36 -> 0.21
B47: 46022 | C47: 15679 | D47: =Beta!K42 -> 67.81 | E47: 457 | F47: =D47*E47 -> 30989.17 | G47: 0.21 | K47: After-tax Cost of Debt (%) | M47: =M45*(1-M46) -> 0.0432288
B48: 45657 | C48: 15926 | D48: =Beta!K94 -> 64.94 | E48: 454 | F48: =D48*E48 -> 29482.76 | G48: 0.21
A50: PEER 3 | B50: Domino's Pizza | K50: Cost of debt (using Synthetic Rating Method)
B51: 46103 | C51: 5135.77 | D51: =Beta!O30 -> 348.14 | E51: 33.82 | F51: =D51*E51 -> 11774.095 | G51: 0.21 | K51: Particulars | L51: Notes | M51: Value
B52: 46019 | C52: 5048.28 | D52: =Beta!O42 -> 425.28 | E52: 34.24 | F52: =D52*E52 -> 14561.587 | G52: 0.21 | K52: Riskfree Rate | M52: =D11 -> 0.04362
B53: 45655 | C53: 5197.24 | D53: =Beta!O94 -> 438.08 | E53: 34.99 | F53: =D53*E53 -> 15328.419 | G53: 0.21 | K53: Credit Spread based on Synthetic Rating | L53: AA | M53: 0.0055
K54: Debt Borrowing Rate (%) | M54: =M52+M53 -> 0.04912
A55: PEER 4 | B55: Chipotle (CMG) | K55: Income Tax Rate (%) | M55: =G36 -> 0.21
B56: 46112 | C56: 5245.88 | D56: =Beta!W29 -> 33.16 | E56: 1301.86 | F56: =D56*E56 -> 43169.678 | G56: 0.21 | K56: After-tax Cost of Debt (%) | M56: =M54*(1-M55) -> 0.0388048
B57: 46022 | C57: 5075.81 | D57: =Beta!W42 -> 37.49 | E57: 1342.62 | F57: =D57*E57 -> 50334.824 | G57: 0.21
B58: 45657 | C58: 4540.62 | D58: =Beta!W94 -> 59.7 | E58: 1376.56 | F58: =D58*E58 -> 82180.632 | G58: 0.21 | L58: ='McD IS'!B4 -> 44561 | M58: ='McD IS'!C4 -> 44926 | N58: ='McD IS'!D4 -> 45291 | O58: 45657 | P58: 46022 | Q58: AVG
K59: ICR - interest coverage ratio | L59: ='McD IS'!B34/'McD IS'!B38 -> 8.9736886 | M59: ='McD IS'!C34/'McD IS'!C38 -> 6.927092 | N59: ='McD IS'!D34/'McD IS'!D38 -> 8.3456055 | O59: ='McD IS'!E34/'McD IS'!E38 -> 7.5836653 | P59: ='McD IS'!F34/'McD IS'!F38 -> 7.6883692 | Q59: =AVERAGE(L59:P59) -> 7.9036841
A60: PEER 5 | B60: Wendy's
B61: 46110 | C61: 4116.59 | D61: =Beta!S29 -> 6.88 | E61: 190.9 | F61: =D61*E61 -> 1313.392 | G61: 0.21
B62: 46019 | C62: 4145.02 | D62: =Beta!S42 -> 8.17 | E62: 194.03 | F62: =D62*E62 -> 1585.2251 | G62: 0.21
B63: 45655 | C63: 4092.57 | D63: =Beta!S94 -> 16.17 | E63: 205.61 | F63: =D63*E63 -> 3324.7137 | G63: 0.21
A66: Source - | B66: Total Debt and Shares O/S data taken from Investing.com for Q1 2026, FY2025 and FY2024 Share Price data taken for nearest date from Beta Sheet (investing.com)

Sheet DCF
B1: DCF Calculation
B2: (in USD million except per Share Data)
B3: Valuation Date | C3: 46203
B4: Latest Filing | C4: 46112 | K4: 1 | L4: End-Year Discounting
B5: Choose Discounting (1 for End Year, 2 for Mid-Year) | C5: 1 | K5: 2 | L5: Mid-year Discounting
B6: WACC | C6: =WACC!O9 -> 0.064577055
B7: Tax Rate | C7: =WACC!I27 -> 0.21
B9: Date of cash flows (end-year) | C9: 46203 | D9: 46387 | E9: =EDATE(D9,12) -> 46752 | F9: =EDATE(E9,12) -> 47118 | G9: =EDATE(F9,12) -> 47483 | H9: =EDATE(G9,12) -> 47848 | I9: =EDATE(H9,12) -> 48213
B10: Date of cash flows (mid-year) | C10: 46203 | D10: =AVERAGE(C9:D9) -> 46295 | E10: =AVERAGE(D9:E9) -> 46569.5 | F10: =AVERAGE(E9:F9) -> 46935 | G10: =AVERAGE(F9:G9) -> 47300.5 | H10: =AVERAGE(G9:H9) -> 47665.5 | I10: =AVERAGE(H9:I9) -> 48030.5
B11: EBIT | D11: ='McD IS'!I34 -> 14154.225 | E11: ='McD IS'!J34 -> 15459.332 | F11: ='McD IS'!K34 -> 16386.892 | G11: ='McD IS'!L34 -> 17370.106 | H11: ='McD IS'!M34 -> 18412.312 | I11: ='McD IS'!N34 -> 19517.051
B12: Tax | D12: =D11*$C$7 -> 2972.3872 | E12: =E11*$C$7 -> 3246.4598 | F12: =F11*$C$7 -> 3441.2474 | G12: =G11*$C$7 -> 3647.7222 | H12: =H11*$C$7 -> 3866.5856 | I12: =I11*$C$7 -> 4098.5807
B13: NOPAT | D13: =D11-D12 -> 11181.837 | E13: =E11-E12 -> 12212.873 | F13: =F11-F12 -> 12945.645 | G13: =G11-G12 -> 13722.384 | H13: =H11-H12 -> 14545.727 | I13: =I11-I12 -> 15418.47
B14: Add: Depreciation and amortisation | D14: ='McD-CFS'!H8 -> 1611.7207 | E14: ='McD-CFS'!I8 -> 2264.9842 | F14: ='McD-CFS'!J8 -> 2348.9096 | G14: ='McD-CFS'!K8 -> 2441.518 | H14: ='McD-CFS'!L8 -> 2543.0744 | I14: ='McD-CFS'!M8 -> 2653.8777
B15: Minus: Change in NWC | D15: ='McD-CFS'!H11 -> 33.14153 | E15: ='McD-CFS'!I11 -> -145.41378 | F15: ='McD-CFS'!J11 -> -153.61634 | G15: ='McD-CFS'!K11 -> -162.83332 | H15: ='McD-CFS'!L11 -> -172.60331 | I15: ='McD-CFS'!M11 -> -182.95951
B16: Less: Capital expenditure | D16: ='McD-CFS'!H15 -> -2375.7677 | E16: ='McD-CFS'!I15 -> -3264.9484 | F16: ='McD-CFS'!J15 -> -3460.8453 | G16: ='McD-CFS'!K15 -> -3668.496 | H16: ='McD-CFS'!L15 -> -3888.6058 | I16: ='McD-CFS'!M15 -> -4121.9221
B17: Debt free (Unlevered) cash flow (Free Cash Flows to Firm) | C17: 0 | D17: =SUM(D13:D16) -> 10450.932 | E17: =SUM(E13:E16) -> 11067.495 | F17: =SUM(F13:F16) -> 11680.093 | G17: =SUM(G13:G16) -> 12332.572 | H17: =SUM(H13:H16) -> 13027.592 | I17: =SUM(I13:I16) -> 13767.466
B18: NPV for Full Year Discounting | C18: =XNPV(C6,C17:I17,C9:I9) -> 59666.903
B19: NPV for Mid Year Discounting | C19: =XNPV(C6,C17:I17,C10:I10) -> 61406.842
B21: NPV for explicit period based of Discounting Method | C21: =CHOOSE(C5,C18,C19) -> 59666.903
B23: Terminal value | D23: Gordon Growth Model | I23: SENSITIVITY ANALYSIS
B24: Long Term Growth Rate | D24: 0.0175 | K24: WACC
B25: Terminal Value | D25: =I17*(1-D24)/(C6-D24) -> 287327.57 | J25: =D38 -> 318.38607 | K25: 0.0566 | L25: =K25+0.2% -> 0.0586 | M25: =L25+0.2% -> 0.0606 | N25: =M25+0.2% -> 0.0626 | O25: =N25+0.2% -> 0.0646 | P25: =O25+0.2% -> 0.0666 | Q25: =P25+0.2% -> 0.0686 | R25: =Q25+0.2% -> 0.0706 | S25: =R25+0.2% -> 0.0726
D26: End-Year | E26: Mid-Year | I26: LTGR | J26: 0.0135 | K26: 361.11961 | L26: 342.94329 | M26: 326.31178 | N26: 311.0363 | O26: 296.95761 | P26: 283.94048 | Q26: 271.86931 | R26: 260.64467 | S26: 250.18063
B27: Time to Terminal Value | D27: =(I9-C9)/365 -> 5.5068493 | E27: =(I10-C10)/365 -> 5.0068493 | J27: =J26+0.1% -> 0.0145 | K27: 368.52801 | L27: 349.61787 | M27: 332.34959 | N27: 316.51836 | O27: 301.95205 | P27: 288.505 | Q27: 276.05306 | R27: 264.4898 | S27: 253.72343
B28: Present Value of TV | D28: =PV($C$6,D27,0,-$D$25,0) -> 203571.55 | E28: =PV($C$6,E27,0,-$D$25,0) -> 210041.76 | J28: =J27+0.1% -> 0.0155 | K28: 376.29692 | L28: 356.60218 | M28: 338.65516 | N28: 322.2332 | O28: 307.14994 | P28: 293.24817 | Q28: 280.3944 | R28: 268.4745 | S28: 257.39033
B29: PV of TV (active choice of endyear/midyear) | D29: =CHOOSE(C5,D28,E28) -> 203571.55 | J29: =J28+0.1% -> 0.0165 | K29: 384.4533 | L29: 363.91829 | M29: 345.24669 | N29: 328.19598 | O29: 312.56395 | P29: 298.18069 | Q29: 284.9024 | R29: 272.60651 | S29: 261.18795
B30: DCF Value of Firm / Operating Business Enterprise Value | D30: =C21+D29 -> 263238.46 | J30: =J29+0.1% -> 0.0175 | K30: 393.02689 | L30: 371.59041 | M30: 352.1441 | N30: 334.42318 | O30: 318.20785 | P30: 303.31413 | Q30: 289.58683 | R30: 276.89415 | S30: 265.12342
B31: Add: Non Operating Assets | D31: ='McD-BS'!G13 -> 2865 | J31: =J30+0.1% -> 0.0185 | K31: 402.05054 | L31: 379.64519 | M31: 359.36918 | N31: 340.93279 | O31: 324.09661 | P31: 308.66101 | Q31: 294.45826 | R31: 281.34638 | S31: 269.20438
B32: Total Enterprise Value of Firm | D32: =D30+D31 -> 266103.46 | J32: =J31+0.1% -> 0.0195 | K32: 411.56063 | L32: 388.11197 | M32: 366.94583 | N32: 347.74448 | O32: 330.24651 | P32: 314.23494 | Q32: 299.52812 | R32: 285.97286 | S32: 273.43904
B33: Less: Gross Debt & Debt Equivalents | D33: ='McD-BS'!G24+'McD-BS'!G31 -> 40105 | J33: =J32+0.1% -> 0.0205 | K33: 421.59761 | L33: 397.0232 | M33: 374.90038 | N33: 354.87976 | O33: 336.67532 | P33: 320.05069 | Q33: 304.80879 | R33: 290.78404 | S33: 277.83626
B34: Add: Cash & STI | D34: ='McD-BS'!G7 -> 1170 | J34: =J33+0.1% -> 0.0215 | K34: 432.20648 | L34: 406.41482 | M34: 383.26181 | N34: 362.36226 | O34: 343.40245 | P34: 326.12434 | Q34: 310.31369 | R34: 295.79119 | S34: 282.40559
B35: Less: Non Controlling Interest | D35: ='McD-BS'!G46 -> 0
B36: DCF Value of Common Equity (Equity Value) | D36: =D32-D33+D34-D35 -> 227168.46
B37: No. of diluted shares | D37: =Raw!H45 -> 713.5 | E37: VALUATION RANGE | I37: SENSITIVITY ANALYSIS
B38: DCF value per share | D38: =D36/D37 -> 318.38607 | E38: Higher Value | F38: =N31 -> 340.93279 | K38: WACC
E39: Lower Value | F39: =P29 -> 298.18069 | G39: =IF(C55 <F39,"UNDERVALUED - BUY", IF(C55>F38, "OVERVALUED - SELL", "FAIRLYPRICED - HOLD")) -> UNDERVALUED - BUY | J39: =D53 -> 418.12416 | K39: 0.0566 | L39: =K39+0.2% -> 0.0586 | M39: =L39+0.2% -> 0.0606 | N39: =M39+0.2% -> 0.0626 | O39: =N39+0.2% -> 0.0646 | P39: =O39+0.2% -> 0.0666 | Q39: =P39+0.2% -> 0.0686 | R39: =Q39+0.2% -> 0.0706 | S39: =R39+0.2% -> 0.0726
B40: Terminal Value | D40: Exit Multiple Method | I40: Exit Multiple | J40: 13.49 | K40: 344.52608 | L40: 340.83493 | M40: 337.18748 | N40: 333.58313 | O40: 330.0213 | P40: 326.50139 | Q40: 323.02283 | R40: 319.58504 | S40: 316.18747
B41: LTM EV/EBITDA Industry | D41: 17.49 | J41: =J40+1 -> 14.49 | K41: 367.47266 | L41: 363.54377 | M41: 359.66151 | N41: 355.82521 | O41: 352.03425 | P41: 348.28799 | Q41: 344.58582 | R41: 340.92714 | S41: 337.31135
B42: Terminal Year EBITDA | D42: =I11+I14 -> 22170.929 | J42: =J41+1 -> 15.49 | K42: 390.41923 | L42: 386.25262 | M42: 382.13554 | N42: 378.06729 | O42: 374.04719 | P42: 370.07459 | Q42: 366.14882 | R42: 362.26924 | S42: 358.43522
B43: Terminal Value | D43: =D41*D42 -> 387769.54 | J43: =J42+1 -> 16.49 | K43: 413.3658 | L43: 408.96147 | M43: 404.60957 | N43: 400.30936 | O43: 396.06014 | P43: 391.86119 | Q43: 387.71182 | R43: 383.61134 | S43: 379.55909
B44: Present Value of TV | D44: =PV(C6,D27,0,-D43,0) -> 274734.68 | J44: =J43+1 -> 17.49 | K44: 436.31237 | L44: 431.67032 | M44: 427.0836 | N44: 422.55144 | O44: 418.07308 | P44: 413.64779 | Q44: 409.27481 | R44: 404.95344 | S44: 400.68297
B45: DCF Value of Firm / Operating Business Enterprise Value | D45: =D44+C21 -> 334401.59 | J45: =J44+1 -> 18.49 | K45: 459.25894 | L45: 454.37917 | M45: 449.55763 | N45: 444.79352 | O45: 440.08603 | P45: 435.43438 | Q45: 430.83781 | R45: 426.29554 | S45: 421.80684
B46: Add: Non Operating Assets | D46: 2865 | J46: =J45+1 -> 19.49 | K46: 482.20551 | L46: 477.08802 | M46: 472.03166 | N46: 467.03559 | O46: 462.09897 | P46: 457.22098 | Q46: 452.40081 | R46: 447.63764 | S46: 442.93072
B47: Total Value of Firm | D47: =D45+D46 -> 337266.59 | J47: =J46+1 -> 20.49 | K47: 505.15208 | L47: 499.79687 | M47: 494.50569 | N47: 489.27767 | O47: 484.11192 | P47: 479.00758 | Q47: 473.9638 | R47: 468.97975 | S47: 464.05459
B48: Less: Gross Debt & Debt Equivalents | D48: 40105 | J48: =J47+1 -> 21.49 | K48: 528.09865 | L48: 522.50572 | M48: 516.97972 | N48: 511.51975 | O48: 506.12487 | P48: 500.79418 | Q48: 495.5268 | R48: 490.32185 | S48: 485.17846
B49: Add: Cash | D49: 1170
B50: Less: Non Controlling Interest | D50: 0
B51: DCF Value of Common Equity (Equity Value) | D51: =D47-D48+D49-D50 -> 298331.59
B52: No. of diluted shares | D52: =Raw!H45 -> 713.5 | E52: VALUATION RANGE
B53: DCF value per share | D53: =D51/D52 -> 418.12416 | E53: Higher Value | F53: =N45 -> 444.79352
E54: Lower Value | F54: =P43 -> 391.86119 | G54: =IF(C55 <F54,"UNDERVALUED - BUY", IF(C55>F53, "OVERVALUED - SELL", "FAIRLYPRICED - HOLD")) -> UNDERVALUED - BUY
B55: CMP (as on 30-06-2026) | C55: 270.3
A57: 1 | B57: Mid year discounting
A58: 2 | B58: Year end discounting
